{"0": ["Russian", "the Russians", "Russia", "Prussia"], "1": ["Paris", "Grisi", "Paris—and an Indian screen", "aristocracy", "Rome or Paris", "their friend of Rome and Paris", "Brisk", "Paris were cell-"], "2": ["tempted", "mansion habituated him", "hated", "seated", "B3", "Dr. Kate", "velvet", "anticipated"], "3": ["beneath his knee", "satisfactory", "benefactor"], "4": ["53\n\nvigour", "Your", "To an hour", "nay", "Sour", "honour", "hour’", "dour"], "5": ["Rome", "weeping women", "Home", "Come"], "6": ["instead of your imagination for all those dazzling\nand interesting objects that make the index-", "well the length of their brother’", "actually proving that this was the best of all", "govern England from the accession of the House\nof Hanover", "Cato", "neither of them making the\nslightest allusion to the catastrophe", "very accurate details as to the cause of", "abounding in all the qualities\nof the", "most speed from Windsor to the Foreign Office", "which it appears to the\nis impossible without getting rid of the flag", "some of them suspecting that\nthis movement was"], "7": ["when she knew that marriage was impossible", "gossip", "Possibly", "us"], "8": ["a gallery of sculpture", "the gallery", "long gallery", "A gallery"], "9": ["sending", "Send", "along winding", "that river winding", "Reading", "tending with", "Senor Mendizabel", "In", "silver-sounding"], "10": ["Rue de Rivoli", "seems", "VOL", "Rue de Rivoli seemed always", "Rue de Rivoli seemed", "Czar"], "11": ["comprised his social relations", "risen", "recognised", "Nay", "authorised", "Treasury", "surprised"], "12": ["Arlington Street at a very late hour", "Berlin", "Arlington", "it’", "Arlington Street"], "13": ["its", "its banks", "its twisted columns", "its opposite bank\nthe boundary of", "its airy pinnacles"], "14": ["Conservative", "Conserve-", "Conservative Associa-", "Amid", "Conservatism", "Be", "Conservatives", "knew of Conservatives"], "15": ["the Park", "and park", "debt—", "Hyde Park", "the park", "lark", "the Park when the Court prorogued Parliament", "Shirley Park", "the Palace", "timbered park", "The Provincials", "The peace\nof Paris found the government of this"], "16": ["not Here", "sat next her", "Wasn’t he!", "was"], "17": ["and placed her arms round his neck", "once celebrated for her genius and her", "and he speaks", "dishes faggots and howls", "loved her mother", "and her love", "The extreme delicacy of her\nappearance was increased by her deep mourning"], "18": ["conducive", "beyond", "despondency"], "19": ["Study", "Stultz", "stuffed"], "20": ["time at Eton", "once to Eton", "back to Eton", "Grobbleton", "I", "TJ", "to Eton", "To Eton", "Eton"], "21": ["the world", "nor for her did the world contain an exit-\nhence", "new world", "the World", "125", "the finest in the world!", "F3", "The wooded heights"], "22": ["Althorp", "wasn’t an", "he’", "not an", "Not an\nauthor", "authors", "As"], "23": ["towns which\nthey never saw", "nor do they\nfulfil", "they\nwere", "They", "least they read very well"], "24": ["allotted gardens", "Reddens", "Carlton Gardens", "Potts", "Ermengarde"], "25": ["which were of course merely", "small park which was table land", "which Mr.\nPitt had comprehended", "which was", "which was the boundary", "which they most warmly", "which was probably the reason he", "which was not", "which is indispensable", "which", "which was probably the reason"], "26": ["feeling in England", "unfortunately for England", "well for England", "cecds", "from\nEngland", "England", "glancing", "sys-\ntem of England is in infinitely"], "27": ["He", "passing for", "ly", "Classics", "Passing", "one pass", "So"], "28": ["Dantesque", "Esq", "ESQ MP"], "29": ["upon", "Upon"], "30": ["Does", "He does not", "does not ask", "does not", "Reform is not such"], "31": ["Augustine", "Augustus", "Both Augustine", "Mr", "unjust"], "32": ["A woman", "woman", "as on woman", "woman’", "A", "yeomanry"], "33": ["feast the county", "amount", "county—", "aunt", "county", "counter", "benefited the county", "sagacity in council", "country’"], "34": ["much", "Such", "Nebuchadnezzar", "life see so much", "“How much", "much lace", "Duchess"], "35": ["brooking familiarity", "King-", "kinsmen", "leaving", "King’", "kingdom knew", "kingdom", "the King", "kicking", "Speaking", "looking very much like\nmartyrs", "Thinking"], "36": ["Indeed", "indeed"], "37": ["Rigby’", "Rigby with", "once to\nMr. Rigby", "trigue", "Rigby", "He surveyed Rigby", "the Rigby"], "38": ["society", "and a very great favourite in society", "throughout every circle\nof Parisian society", "Society", "anxiety", "treme sobriety"], "39": ["knowing", "Knowledge"], "40": ["America", "sojourned in Africa", "Africa"], "41": ["previously", "be-", "had graciously bestowed on him", "various", "unconsciously"], "42": ["whether", "whether he knew", "whether Ireland", "whether Ireland was to be\nconquered", "Ireland", "whether he be a monk in his cloister", "from Ireland", "whether it be looked on as\na premature movement"], "43": ["Emperors", "Mexico", "perplexing"], "44": ["E", "Because", "Clause"], "45": ["Northern", "Therefore", "Here’", "therefore", "Nowhere", "Institute where there were a library and", "he", "Where am I", "hitherto", "There", "though there were several of fences", "There’", "together", "rather", "Here", "Theresa"], "46": ["the vast avenues", "vast and ornate", "Revenues", "avenue Marigny", "were vast"], "47": ["Music", "Neapolitan", "Neapolitan physician"], "48": ["Accordingly", "Accord-", "cording to Hippocrates"], "49": ["so particularly", "Sparta", "which he particularly resolved", "particularly", "which he particularly", "gardens of which his niece was par-\ncircularly fond"], "50": ["given", "gives"], "51": ["Europe", "is", "European", "Euro-", "the South\nof Europe", "quieted Europe", "Property", "the European"], "52": ["save", "Maltravers", "Ravenna"], "53": ["lion’", "Trillion’", "Rebellion"], "54": ["“I believe it might all be done for two\nor", "We believe we may", "relief—", "Lyle’", "T believe", "I believe"], "55": ["Departures", "posture", "Regular features", "Adventures"], "56": ["Marquess", "Unquestionably", "Conquest", "Ques-"], "57": ["subsisted between him and the former object\nof his concealed tenderness", "He held forth his hand", "gem", "Had\nhe forgotten his grandfather", "Le Grange", "tripped on his toes"], "58": ["Vanquished", "she refused", "Gentleman Usher", "Townshend", "Archbishop Usher", "She"], "59": ["TI wish", "I wish"], "60": ["Newspapers", "Tapers", "Taper", "scrapes"], "61": ["Chartism", "Chartists", "Judaism", "article—", "Charta"], "62": ["Lancashire", "curved in Lancashire during the preceding", "Lu-", "Christmas", "Christmas in Lancashire"], "63": ["occasionally", "Occasionally", "It’", "F", "occasionally nodding his head", "occasionally nodding his", "very rarely do they occasion one"], "64": ["very bitterly when", "which latterly he never quieted", "Latterly", "eagerly", "A masked battery of canister and grape could\nnot have", "paid quarterly"], "65": ["Taper beat Tadpole", "Tadpole", "Mr.", "with Tadpole", "Mr. Tadpole"], "66": ["poised to hear that there was still", "every subject which can interest the public mind", "contingency that was not the subject of", "views on that subject", "Ject", "and vowed frequently that she was not\nweeping for herself", "so\nthat they would not insist upon the reciprocity", "gauges that were not long strange to him"], "67": ["at", "English", "lishman", "boyish", "Manhood"], "68": ["Westminster", "stern", "Western Europe is organized and prince-", "Manchester", "D3", "Western", "Master", "Modern", "nest"], "69": ["the Anti-Corn\nLaw League", "The Age", "The Arch-Medio-", "itself the apex of", "the arena", "soared in the air", "the Arabian tribes rank in the first\nand superior class", "the antechamber"], "70": ["Til", "latitudinarian", "Utilitarian", "Austrians"], "71": ["Why", "why"], "72": ["Well", "and well-registered", "well that not", "unwell", "already well beneficed", "Israel"], "73": ["Bolton", "“Tam", "and Mr. Melton", "He rallied Mr."], "74": ["unfulfilled", "Richmond villa", "induced Ville-", "Seville", "Ville-"], "75": ["views", "oO", "Jews"], "76": ["one could ever comprehend", "and courted", "Agincourt", "places at Court", "sixth", "Palladian palace\nwith wings and colonnades encircling the court", "center and resigned power in the course of\nthree days", "she curtseys", "the Court"], "77": ["In London", "London", "to London", "LoNdon", "from London", "The City\nof London", "way to London", "in London", "LONDON", "annum"], "78": ["To women however", "however", "However"], "79": ["temperance", "In France", "France", "of France", "Dance", "in France", "He balanced", "chance-medley maxims", "france", "Frankfort", "Frankly"], "80": ["with an air of kindness", "once with as much dignity and", "refined dishes with all the intrepidity of saucy\nignorance", "as", "with an arch grace", "with an insinuating smile", "with an\n\nP2", "Club", "He felt as an Egyptian", "with an object", "Rigby with an inquiring"], "81": ["called", "modelled", "Called", "the\nvalley", "called forth"], "82": ["heard", "Pardon", "Harry", "Hardly", "Spaniard"], "83": ["Tories", "Oriel", "pseudo-Tories"], "84": ["Meyerbeer", "Peer", "speech"], "85": ["which city", "city—", "which adversity and\naffliction", "at which city it may be said he"], "86": ["did", "Edith was reading", "Edith", "from Edith", "self and Edith", "Sedition", "of Edith"], "87": ["without reserve", "Without", "acquired without an effort", "without", "not without"], "88": ["devoted to each other", "Otherwise", "stirrup-leathers", "others", "and a few others", "herself", "would insist that all others", "Fetherstonehaugh"], "89": ["Youth", "you'", "“Try you", "young", "You"], "90": ["tell you", "resolved to tell her all", "tell me what", "tell us that from time immemorial\nthey", "Tell", "Stella", "tell you to", "Tell him", "The traveller fell into", "tell us", "Intellect"], "91": ["and Henry Sydney and Buckhurst", "Sydney", "our Henry Sydney", "and Henry", "and Henry Sydney", "and Sydney on the scaffold"], "92": ["this Sidonia", "Sidonia", "Medina Sidonia and Cadiz to\nits dark", "and a Sidonia", "and Sidonia", "that Sidonia", "Let", "side as Sidonia", "and Sidonia with", "hotel of Sidonia"], "93": ["Miserable", "Gay", "Aragon", "Arabia", "Arab"], "94": ["wife’", "life—here", "life", "vilify"], "95": ["ingham", "Nottingham", "Birmingham they found", "Everingham", "Birmingham", "yataghan"], "96": ["spell-bound", "rounded", "you found", "and found", "treated a profound subject with", "Stella found", "profound"], "97": ["Turning", "Perceiving\nConingsby", "stated Coningsby", "As for Coningsby", "Alone with Coningsby", "CONINGSBY", "Coningsby Castle", "and Coningsby’", "fortunes of Coningsby", "Coningsby home", "Coningsby’", "until he learned that Lord Mon-\n\f\n306 CONINGSBY", "Canning", "Conings-", "attracted Coningsby’", "a3\n\f\n344 CONINGSBY", "often were her sunny eyes directed to Coningsby", "Coningsby bade his friend farewell till the mor-", "from Mr. Coningsby", "Coningsby at Eton", "Here is Mr. Coningsby", "unintentionally convinced him that\nConingsby", "young\nConingsby", "Coningsby", "Mr.\nConingsby", "Coningsby pressed his grandfather’s hand", "simultaneously with Coningsby’", "and that Coningsby"], "98": ["Each", "L2", "each", "roach"], "99": ["Leicestershire", "Hertfordshire", "shire", "Yorkshire town", "Berkshire"], "100": ["Nor", "Grosvenor Gate", "Normans", "Northamp-"], "101": ["would", "Would", "should be taken unawares", "Thus", "scarcely could have hoped that he would have"], "102": ["none of us do", "stalls of St.", "statue of Commerce", "district of one of the", "Is", "Nor was this one of those transient tempest\nthat often agitate the summer"], "103": ["Coal Committee", "Committee", "Admit"], "104": ["though formal and monoto-\nnous in its general character", "Biggs", "their characteristic want of grandeur", "amount of what is termed Character by", "had a harsh and metallic character", "new characters"], "105": ["moody", "nobody", "so", "Nobody"], "106": ["soon", "boon", "Soon", "and as soon"], "107": ["her virtues", "many virtues", "her work", "her visitor"], "108": ["soften", "often", "sunbeam as often", "very often not", "soon often", "Often", "We", "very often not your-\nself"], "109": ["These", "Her tones were tremulous", "but those were words\nand dreams", "these were", "calm as if he were winning the St.", "these were chiefly left", "the Whigs were\nobliged to make", "These kept somewhat"], "110": ["Lord’", "Lord", "Flora", "Lordship", "Lord-", "once on Lord Esk-"], "111": ["Buckhurst", "contradicted Buckhurst", "Buckhurst added", "and Buckhurst", "Palmer it was Buck-\nhurst", "for Buckhurst", "Buckhurst’"], "112": ["and assuring their neighbours with", "until arriving at their limit", "Their", "rub their hands", "their habitual tone", "their followers that which", "their new", "their vicinity", "Nor did he do their opponents\nless justice", "their worst apprehensions", "their forms and composed their groups", "their"], "113": ["the Upper Park", "Lower Park", "Upper Park that", "the Upper\nPark", "Upper Park"], "114": ["chine", "China", "Sinai"], "115": ["Languedoc", "was free", "freedom", "Dukedom"], "116": ["that he has abruptly closed", "and that he should\nhave billiards", "had been", "haunting her heart with the recollec-\ntion that she had been the unconscious", "Marshal than he has of being", "forth all that had occurred", "and that he had\nseen"], "117": ["the church", "the Chinese of", "the Church and the\nCarnage were convoked", "He assured Coningsby that the Church", "Church", "history of Church"], "118": ["gave place to his intelligence", "placed", "Placed", "self-complacency spread"], "119": ["four years\nago", "years ago", "four years ago"], "120": ["of a brain", "Traitors", "tea-tray", "San Benito", "a3", "Moors"], "121": ["lady’", "” her Ladyship", "Lady"], "122": ["is a\nJew", "is a Jew"], "123": ["forest", "inn", "Forest\nInn"], "124": ["Besides", "four and mark of high", "four and mark of high consideration"], "125": ["cold", "Reynolds", "Surrey", "old Age", "Kangaroo Grey"], "126": ["competed", "quieted her", "disquieted", "squid"], "127": ["scarcely able to repress", "Scarcely", "scarcely numbering at\nthat"], "128": ["Almost", "T almost", "most women"], "129": ["once", "Hence", "bowed as to beings set apart for reverence and\ndelicate treatment", "Once", "hence", "Whence", "silence—", "Providence"], "130": ["About", "Juno", "CHAPTER V.", "CHAPTER V.\n\nAbout", "CHAPTER III"], "131": ["obtained nearly", "weary", "curly", "nearly", "carly"], "132": ["fresh from Eton", "from Burke", "her from her", "from Henry"], "133": ["This", "his", "Add to this"], "134": ["Secret-", "Lucretia", "Screw", "By", "Secretary of State at thirty", "Crecy", "Those who were convicted of secret Judaism"], "135": ["we shall see", "“I know I shall not give up", "“I know I shall not", "I shall be very\nhappy to be of service", "then I know that\nmonarchs are serious"], "136": ["strong-minded", "so strong", "patron’", "Ministry"], "137": ["possessed", "Or", "dress", "At", "Expression", "expressed", "dressed", "dressed in\nstyle of ultra fashion", "self-possessed", "dresses"], "138": ["Slough to the College", "the college", "their college dreams", "College"], "139": ["the valley", "where he was to succeed by\nthe aid of the Wesleyans", "The oak roared", "the grassy sward", "the Buck-hounds", "The Duke", "the Malayan", "the Russophobia", "the tears", "the Tartar", "the Hall", "the State", "the Brazil", "The Dominicans"], "140": ["length", "Helen", "talent—", "held"], "141": ["Nor could he indeed by any combination see\nthe means to extricate himself from the perils\nthat were encompassing him", "flung himself", "himself at fault", "developed itself", "whims", "myself", "Himself", "Seltzer", "himself", "himself at Eton", "Grey himself", "And himself", "who seating himself by her side"], "142": ["higher", "Highland", "Her", "Chudleigh", "Highness", "Whig"], "143": ["Culloden", "Tusculum", "Lucullus"], "144": ["whose name\nI", "name is Legion", "whose guest for", "Who—-who"], "145": ["After", "after", "After that much"], "146": ["Sévres", "Resale", "result", "resting", "resolute", "Representa-"], "147": ["Millbank", "Albanian", "Millbank’", "Here is Mr. Millbank", "Albany", "then he remembered that\nMr. Millbank"], "148": ["Isabel", "Mendelsohn", "Rebels"], "149": ["Sedgwick", "To", "pick", "so quickly"], "150": ["Bully", "painfully\napologising for", "successfully", "Pray", "BS", "Bully Block", "Spain", "Painfully"], "151": ["Library", "the library", "every Eton man would be as proud of his name\nbeing registered as a donor in the Catalogue of\nthis Library"], "152": ["Tis true", "if true", "struck", "Rue Trenches", "truth"], "153": ["Naples", "his dynasties at Naples and\nat Milan", "ter at Naples into", "two\nmiles out"], "154": ["grace", "Saracens", "Your Grace"], "155": ["Olynthians", "Lady St. Ju-", "Rue St. Florentin", "St. Julians", "Lady St.\nJulians", "Lady St. Julians"], "156": ["Universities", "Liverpool", "varsity", "University opens to youth", "Poitiers"], "157": ["such as Derby can alone produce", "and produces", "legal", "prodigal", "Problem"], "158": ["When", "when a youth of still tender", "when", "Phenix"], "159": ["Be-", "two years\nago that", "fears", "two years", "least nearly two years", "two\nyears", "Caesars", "two years that\nfollowed"], "160": ["tleman appeared", "Are-", "Square"], "161": ["illiberal—", "Degenerate", "independent of her general\nrevenue", "trast to St. Geneviéve!", "General", "B", "generally", "generally known"], "162": ["Might", "Brighton", "and you might often", "Enlightened-Spirit-of-the-Age", "clear-sighted", "might"], "163": ["really", "Sir", "equally striking", "equally", "equality as equally pernicious with"], "164": ["so “slashing", "Nothing", "laughing", "tell her nothing", "things", "nothing"], "165": ["the broad fields as far as eye\ncould", "Eton field-marshal", "A Field\nMarshal", "A Field", "Fielding", "Field-"], "166": ["“I am afraid you", "said", "“I am sorry"], "167": ["Affairs", "First", "case fairly", "titular state of affairs before", "affairs went on flowingly\nenough"], "168": ["L3", "were at least men of\nintellect and courage", "at least gave", "but at least it was\nan intelligible compact", "least an on-dit", "berry-leaf", "least injured\nyou"], "169": ["takes", "the lawn", "the lake", "The Liver-", "the wild fowl covered the\nwaters of a lake", "the lack-lustre\neye"], "170": ["brow", "hotel", "gave evidence at the inquest", "at the hotel in Brook"], "171": ["dividing very nervously some grapes", "I am very happy\n\f\n42", "and I am told it\ngoes down very well", "very\nhandsome", "and Vere", "new carpets and old hangings", "and were often very acutely\ncanvassed and _", "“and very handsome"], "172": ["ladies", "Miladi", "Milan"], "173": ["Amersham", "Burnham", "Durham"], "174": ["knew so many worthless", "carelessly", "doubtless", "lessly"], "175": ["Finally", "originally interested", "originally", "interested", "interested a young\nmind whose active energies were beginning to stir"], "176": ["not", "Ay", "Not", "not broad"], "177": ["yet as your business", "Happiness", "happier", "Manliness", "ingenousness"], "178": ["supposed", "Nor was it displeasing to", "Supposing"], "179": ["mons", "money", "Monte", "summoned", "Monarchy", "gone"], "180": ["Berlin and St. Petersburg", "St. Petersburg", "Augsburg", "Petitpoix", "Petersburg"], "181": ["“ Parliamentary", "Parlia-", "Carlist"], "182": ["and from which the", "and seldom an evening elapsed in which", "and Caryatides\ncarved in dark oak", "and in which he", "Richmond which", "and for which he was\npreparing the nation when the French Rev-\n\n12\n\f\n172", "by a thousand little arts\nby which he carved out work for Gay which", "and which is in general so", "similar in magnitude\nand effect to that which in the preceding", "and in which he possessed considerable", "and for which she\nhad projected a new dress of eclipsing"], "183": ["Whatever", "I implore—whatever\nyou like", "whatever may\nhave been their faults", "What", "whatever", "whatever may have", "what"], "184": ["Cortes", "Shortly", "Whites’", "Corporals"], "185": ["will come\nand see you every", "Everything", "every", "Never", "every hearth", "and a coat of broad cloth for every\n\nn 3\n\f\n274", "every place is", "very", "every wish that she could express", "I ever knew", "every means and every", "very justly", "Every", "slavery", "every intimation that was\nnecessary", "every device that"], "186": ["and national greatness", "irrational", "affectionate", "Hurrah"], "187": ["Not entirely", "Rely"], "188": ["Prelate", "Plateau", "Later", "Watertown"], "189": ["Caput\nMortem", "reputa~", "Caput April defer", "Caput"], "190": ["At length M. Villebecque", "becque’", "Villebec-", "Villebecque"], "191": ["May-Day", "days", "Always"], "192": ["friend’", "ship—", "titular confectionery", "titular friendships"], "193": ["Poland Street", "Downing Street", "H 2", "The broad street was so crowded", "Street", "St. James’ Street", "in Street", "the street"], "194": ["with facility\nand in an instant", "constituency", "Juggins", "and institutes"], "195": ["Desperate necessity", "Princess", "Princesses"], "196": ["Desert", "Certainly", "certainly seemed more to her advantage that", "Aquitaine", "Certainly\nManchester is the most wonderful city of modern\ntimes !", "vainly"], "197": ["and a vast spread of gorse\nand fern", "and a reading hall which any one", "193\n\nread", "and returned him in\nkind", "St. John really made\nhis escape and retired to", "and read"], "198": ["Beautiful", "Beau-", "situate in beautiful gardens on the banks of the\nThames", "surrounded by beautiful meadows", "beauty", "Is she so very beautiful"], "199": ["Jong", "sonages", "Jobson", "Song"], "200": ["Forms-", "Forced", "for", "Fortunate", "whom for", "forget"], "201": ["Aquatic", "Aspasia", "Egypt-", "Asiatic"], "202": ["sufficiently trifling", "eminently", "faintly smiling", "Dog"], "203": ["town for Scot-", "“for I", "“for I\n\nam one", "we answer for him", "for who", "least\nfor the"], "204": ["Wesleyans", "unceasing billiards", "Kellingley", "Hoadleys", "Billingsley", "new feelings", "Lysippus"], "205": ["title", "the castle", "Castle", "Newcastle", "sleepy\ncastle"], "206": ["into a hall of great dimensions", "very greatly expanded", "at a great family congress held at\nNaples", "GREAT city", "with great warmth", "war", "confused and mingled\nsympathy with some great political truths"], "207": ["gentle in livery coats", "Little", "very little", "little foreseeing what", "and every little squire"], "208": ["sweet", "week’", "answer", "meet"], "209": ["Robinettas", "Biron", "Baronet", "Bar"], "210": ["up to Westminster", "A West", "Lepanto", "into", "into Weston’"], "211": ["wald", "Oswald", "Mr. Donald", "Lay"], "212": ["279\n\nnonsense", "sunset", "sunny"], "213": ["And", "wand", "sanders", "She wanders", "four-in-hand", "and", "Me-", "Vandyke"], "214": ["than the gives and trammels of\noffice would", "and the deer based on the\nknolls that", "and that\nhe ought to seize the opportunity of", "and the most", "the Move-", "the sunny glade\nand the solemn avenue", "“and yet I am most", "and Rowland Hill the divisor of the\ncheap postage", "and the least", "and the wealthiest", "and the clamour"], "215": ["Weimar", "Lima", "Married"], "216": ["Continues", "and continual"], "217": ["really have thought it would be yours", "soft and sunny though", "Though", "“and though there is still", "Although", "though a whole\ngarrison was ever on the watch to prevent her", "her thoughts were often in her Saxon valley", "thought", "though were I to", "although all bowed before her", "though it must be owned", "although"], "218": ["Twenty-", "five-and-twenty!", "twenty-nine not five remain", "twenty", "twenty-one", "five-and-twenty years every", "four and twenty"], "219": ["like many critical epochs", "cynical", "the Ecclesiastical", "nice"], "220": ["Cambridge", "Cam~-", "Barnes’ on the bridge", "Staley-bridge", "Staley-Bridge", "often recurred to at Cambridge"], "221": ["new scheme", "new Alcibiades", "Schedule A", "Esk-", "Hem", "so vehement", "knew", "A cheese"], "222": ["Italy", "hospitality", "having visited Italy"], "223": ["the fact that", "the fancy", "fancy", "and fancy", "If"], "224": ["mouth’", "mouth", "Lady Monmouth", "Monmouth", "Monmouth House", "mouth and dine at Monmouth House", "Indeed Lord Monmouth", "Marquess of Monmouth"], "225": ["Dictator", "statesmen", "hesitating", "Etat"], "226": ["which he looked upon as very", "which he opened", "which elsewhere", "which he told", "though its contrast to that\nwhich he expected", "reminded her of the readiness with which he", "which he quieted", "which he much desired", "which he went over", "which her", "which he told\n\f\n200"], "227": ["needed with her chicken-pie", "with", "breakfast with", "Within", "both waiting with equal", "neck with the fondness of\nremorse", "With", "the gamest with", "and ’is so pleasant to talk with one", "with women", "and with rather"], "228": ["During", "loitering", "Considering", "scoff", "swearing", "na’", "offering"], "229": ["Reform", "Before", "before very long", "before"], "230": ["are of Hebrew", "Hebrew", "The Hebrew", "The Hebrew is an"], "231": ["Sovereign", "overwhelming", "Vere"], "232": ["Goodall", "two o’", "and a good number of\nboys in lounging", "two", "two good"], "233": ["their old boroughs", "Luxborough", "Marlborough", "throughout", "the borough", "Luxury"], "234": ["neglected his wife", "somewhat earlier than usual to his chamber", "reminded him that it", "that reminded him of his school-days", "all his sorrows"], "235": ["quailed", "Verily", "Gaily"], "236": ["and short", "distant and splendid city", "and eloquent", "and so", "and a brewer", "Grand Cairo", "clear and sunny", "and leaning", "And now as rumours", "and starting", "so practical and so independent—"], "237": ["Past", "scholiast", "Pasta or"], "238": ["Lucian", "Lucian’"], "239": ["experience—", "Experience", "principle and expediency", "in"], "240": ["divided", "clear-headed", "curly-headed urchins with demure looks", "added", "pervaded all things", "jaded"], "241": ["bowed", "witnessed in those polished\nand luxurious circles", "nic power", "those bowery", "the bowery meads of Eton"], "242": ["Thebes", "then", "Athens"], "243": ["Horse Guards", "and a horseman at full\nspeed", "new horse", "morsel"], "244": ["no hope", "the frenzied hope that\nblends inevitably with absolute ruin", "I hope", "What hopes", "hoped"], "245": ["wildly", "Ill", "He will", "Willesden", "I will myself give it", "Hilloa", "will"], "246": ["especially at Paris", "triennially", "especially if not altogether", "especially", "specially", "especially if not"], "247": ["born", "born at Rome", "stubbornly"], "248": ["Con-", "Conger-", "time an orangery", "ger", "Confer-"], "249": ["Venetian", "Peruvian\nInca", "its brilliant colour", "lian", "liancy"], "250": ["head", "her head", "and bows her head", "turned her head", "her arrival", "bear her"], "251": ["and Radicalism is\npollution", "Radicalism", "Liberalism"], "252": ["afford", "afford him Clarendon and Burnet", "Oxford", "Dartford"], "253": ["may be corrupt", "abruptly", "February"], "254": ["Madrid", "Mademoiselle", "Pride", "Madam"], "255": ["we may all", "Above all", "Pall\nMall", "Pah", "Pall Mall", "in Hall", "Palladian", "pallid"], "256": ["throughout the district that\nsurrounded Beaumanoir", "Anon", "Beaumanoir", "noisy", "TU", "Memoir-", "beneath whose roof at Beaumanoir"], "257": ["often very much perplexed and harassed", "barrassed", "harassed", "Espinasse or", "whose fancy is harassed with", "No-"], "258": ["Lower House", "Thousands", "House"], "259": ["superior to that of a sponge or", "that flash", "that—", "Carthage", "That’", "That is why I", "that", "that’", "That", "in amusing that young\nlady"], "260": ["Notwithstanding", "Staél", "Circumstances", "Hindostan", "stand"]}