{"0": ["devom", "d'm", "Suevo"], "1": ["Crispola", "Bispo", "l0", "Cm", "Iae\ndo Bispo...", "DBispo", "moyeu"], "2": ["acostiadu", "Costa", "Conselleiro Costa Barroso", "Arcos", "Roevista", "Costa ue", "n0", "Hstacuu"], "3": ["ntesllo", "eantes", "Avantesmas", "utl-", "tesla", "Sll", "Esli"], "4": ["IBarrol", "Barrolo", "Ilarrolo", "Iarrolo", "Barrole", "santa mae do Barrolo", "llurrolao", "WBarrolinho", "larrolo", "Barrolos", "HBarrolos"], "5": ["d'Airica", "Airica", "Airica-", "Alrica", "MIrica"], "6": ["I0", "earga", "lve u\nrga", "Lnrga", "Isear", "d'apear", "-iDh", "sarga", "rabear"], "7": ["Icnto", "Ilncntld", "Vss", "Bcnto", "Oh Bcnto", "Bnto", "Ilcnto", "Hcnto", "vrniz dos sapatos-aprescntou a"], "8": ["Caeadas", "Lousadas", "Inurmuradas", "Vadas", "ahfadas", "Wortadas"], "9": ["bom it", "Bom Ieus.l", "bom fm", "bom rcndeiro"], "10": ["cabo d arapau", "cabo d'ouro", "luneta d'ouro", "cabo d'ouro la ltteta d'ouo", "cabo d'aljafar da sombrinha", "cabo dec\nanta", "cr d'ouro", "cabo d'osso do guarda-sol", "qle", "caboea", "cabo do renque d'alamos"], "11": ["fcno", "Iuor", "suor", "Fdo", "Iuo"], "12": ["incendio do Pala-\ncio", "incendio do Pala-", "doeo paz", "fgo"], "13": ["cntrever", "cntreter", "atrever1", "revelacbcs", "ji"], "14": ["hoet", "t]e", "murle d'hoe", "Ioema", "hoem", "cl"], "15": ["Urassn", "assoibo", "Alm d'isso", "ILg0", "Fr", "S", "fugisso", "sc eh0Vasso", "cancassol iNada", "caonfuso cancasso"], "16": ["kF realnto", "Sigaa Real"], "17": ["aquelle", "E.\nn'aquellve", "N'aquelle", "Iaquelle", "monte aquello", "nntquelle sileueio", "naquelle", "Aquelle", "affronta daquelle cnjado", "n'aquelle", "S.\nulgenciol ue aquelle careea obeso", "lGonealo qte aquelle", "quelle", "aquelia"], "18": ["Castello de Peronnc", "Castello de tSanta", "Castollo", "Castello", "Castellos", "Castella", "castellania famosa", "Castellto"], "19": ["u\nIct sag", "Ict", "hem sa-\nes"], "20": ["Santa Mlarla de Craquede", "Santa Maria de Craquede", "Santa Mlaria de raquede", "Santa Maria de Craquedel", "santa Mlaria de Craquede", "Santa Maria de Craqutde", "Santa Maria de Crauede", "dec\nanta Maria", "Santa Mnria de Craquede", "Santa Mlaria de Craquede", "Santa Miaria de Craquede", "Santa Mlaria de Craqude"], "21": ["Magnlfico", "lagine", "maginei", "Imagina", "rvelandu imaginagio", "g-", "prineipio", "nei"], "22": ["Chronica", "Chaonica", "Monicas", "Chrnica", "Thessalonica", "Mlonicas", "Annica", "Visigothicas"], "23": ["Bara\nlas Marges", "crge n", "larges", "Iario das Mlarges", "Mluarges", "Baroneza\ndas Marges", "Mlarges"], "24": ["acudiu", "sacudid", "lrudieao", "Jaraudiu"], "25": ["semelhanga", "melha", "Vermelha", "vermelha le sade", "barrete vermelho"], "26": ["Manoel uarte", "Manoel Duarte", "oManael Duarte", "St I"], "27": ["re salve  ra-", "Iiuy Saloon's Iines", "viuya", "Ti16"], "28": ["Vidago", "agonisava", "alagoVa", "enechia\nagola", "Iagoas", "cafie", "Li", "Gago", "Thiago", "eagoar om", "tago"], "29": ["Quc\ndiaho", "diabol", "diaho"], "30": ["Esquadrinhou", "Pelourinho", "palvarinhos", "srrir", "hurrinho"], "31": ["Poto", "pote  biobo", "Gotoso", "reahotoand0", "Il"], "32": ["l'ara", "tararaml raiamtaml", "Cara-", "Iaradiula", "bai\nara", "Iara", "teaduearam", "at\nAraj", "d'alvigcaras", "lraraes", "larar", "ara", "caraeter", "Ilaras", "Azurara"], "33": ["Ylyia", "uvo", "CO", "tendal", "attender", "Tende", "Iendera", "ntendo\ntiio", "entendienlo"], "34": ["elcico", "Tlo", "ER", "Gazeta", "Gazecta do Ioreo", "Gazelc", "iazer"], "35": ["passadigeo de traves", "atravesol", "Atraz", "cnoravel ivcnda", "atravez d jardin", "tetl", "Atravcs", "atravez tdas en-\nteneas ovuhgelicas", "Atravcs do vco", "atrave", "atravez d matto", "Atraves", "Atrave", "Cnde d\nTrava", "atravez do feljoal"], "36": ["cidnde d'Oli-\nveira", "Nn", "l'oli-", "l'o-", "Oli-", "TZn"], "37": ["Puco", "buco", "ILreuco", "Mucolieo"], "38": ["Contu", "Bonto", "Conto", "Contiuu", "Nonto"], "39": ["Titulo", "Lisboa tres Capitulos\nelle", "Cupitul", "Capitnlo", "jejltt", "Capitanea", "Capital", "Capitulo"], "40": ["lipu", "Cendfe", "d'onde pendia", "crescendo0", "cendia", "suspendia", "rescendia", "Yendiha", "cstendia"], "41": ["Solha", "Olhte", "iolha", "Olha", "tSolha"], "42": ["Craqutde", "Craquide", "Nl", "Iraqucza", "Craqude", "Craque-", "Craquile-", "Craqucde", "ul baquc"], "43": ["isper0", "Ispi-\ngal", "ba csperana", "brotuvn s\ninesperadamcntc", "perc"], "44": ["apetrcehad", "cehi"], "45": ["libeira", "IBen-", "ibeira\ndo Coiee", "Ribeira", "Iibei-", "IBeI", "Iibeiinh"], "46": ["mascnand", "dminando", "elupinand", "dominanda"], "47": ["Iois", "Ilois", "PUois", "kF", "beois", "Ieois", "l'ois"], "48": ["golpcs", "Golpho\nPersiceo"], "49": ["... Alm", "Crz das Almas", "tos almnas", "Feitor-mor das Alfandegas", "Cruz das Almas"], "50": ["Graeinha", "CGraeinha", "s6", "teriria\nraeinha", "raeinha", "traeinha"], "51": ["r0Sa Sopa", "kFu-", "Sopa", "sa dcssa situacio tio falsa", "lica Sonta"], "52": ["Iracejandao", "Naeejas", "valent6es de Nacejas.n", "Nacejas"], "53": ["z-a-\nL-", "joe-\nlhos", "toa-\nlha eom n", "loriga de ina-\nlha", "pa-\nlhioea", "toa-", "toa-\nlha"], "54": ["liherdade d\nCnasco", "av", "goso de verdadciro", "Cerda", "Cerdal"], "55": ["IilNin", "meninu", "menin", "enI-", "meniaon"], "56": ["Nimes", "uipproxime", "Gomes", "IME", "mesm0"], "57": ["Turras", "Turre", "Turrc", "besteirus\nqc eurregira us", "urre", "Iurre"], "58": ["lleicao", "Eleicaio", "Eleicao", "kleicao"], "59": ["Siu", "Positivamente", "nicamente", "assohiando va-\ngamente", "pessiuamentel", "Iament", "Pessimamente", "ulvorocadamente", "divinamentel"], "60": ["Titi", "Tit", "TIt6", "mn sitio", "ITit6", "Tit6-", "Tit6"], "61": ["sc de-\nII0O'aYa", "k s6 de-"], "62": ["Estive", "Pelestina", "Nom", "Ah", "Pales-\ntina", "Palestina", "Destino"], "63": ["llymno da\nCarta", "ma\nca", "comeeo da\ncampanha", "nmna\ncasna", "im"], "64": ["Depais", "miais", "MIais", "Iais", "MIais antigo"], "65": ["Pegas", "uc", "Yillegas", "Yilln"], "66": ["Inanchava", "kEu", "concha", "desmnanchava", "Ianchasse"], "67": ["arremettida", "arremessand", "Mrremessado"], "68": ["ereads", "aceadu", "bua semeadura", "Naa", "meads"], "69": ["asa de Franea", "Historia de Franca", "so", "Rel de Fraaca", "Roet de Franca...", "Roet de Franca"], "70": ["orgnlho", "Ienlto", "genlc", "enlh"], "71": ["Sis", "Yalha", "trabalhadu", "esbogalhava", "trahalhar", "Im alto vo de gralha", "trebalha", "Palha-Ca"], "72": ["Iner", "Ineu", "Inesmo", "Ine", "Inerosos", "trineando"], "73": ["snras", "t[Ue", "Snr", "Snr l", "tSnr"], "74": ["T0thpe", "ci", "Cns", "nio\npcnsci", "pcnsaud", "Pcnsou"], "75": ["mandadu", "anda", "vianda", "Mlanda", "jand", "Mtandarim", "Andtce"], "76": ["lE", "poltron", "muvia da poltrona", "trondo"], "77": ["C0I1", "manla1", "Canla-Pelra", "Iof", "pelra", "Canla-Podra"], "78": ["Convidado", "Conviviam", "iim", "convile"], "79": ["comerm0s", "rome", "comezaina", "Comedla"], "80": ["lPortngal", "portcira", "eahca", "i Portolla", "Portgl", "Porto", "Ci", "Porta", "Portolla"], "81": ["aldizer", "aldca", "Maldio", "alda"], "82": ["I0s", "ln\ngr0sso", "II0s", "I0ss", "uUhl a0Z g'0ss0"], "83": ["lIl", "Elim", "elIl", "elizmcnt", "lildzes", "Mlelieval", "elil", "entlilnenlt0"], "84": ["Cu-\nvalleiro", "Calleiro", "casa du Cavalleir", "cavalleiro", "Cavallei-\nro de", "Cnvalleiro", "Entia Cualleiro", "Cavalleiro", "Cavalleir", "Cavalleiro-quo", "pranchada de cavalleiro", "Cavaulleiro", "intimidate do Cavalleiro", "Cuavalleiro", "avalleiro", "Cavalleiro-", "Cohl  Cavallei-\nro", "Cavalleira", "Cavalleiros d'Ilespanha", "Caval-\nleiro", "Cavallei-", "Ca-\nvlleiro", "Uavalleiro", "Ca\nvalleiro", "Nau", "io do Cavalleiro", "An-\nde Cavalleiro", "Cavalleirol-Cuinhavam", "braco do Cavalleiro"], "85": ["rega0", "agoa do regato", "Itsa", "Carregada", "Arega", "encalrregaa"], "86": ["sobinho", "Audrcsinho", "Templosinho", "risinhos", "Trtesinho", "Ssinho", "piquesinhos", "antol  ruborsinho", "NtUninho", "ssinhlo", "Mlanelsinho", "viuya Pinho", "Templosinho du Amr"], "87": ["-.A cleieio cst:i segtura", "Iei", "Fl-Iei", "Inquiriei", "Ieio", "Ieits", "Ieis", "ca\nIeita"], "88": ["Sbedo", "bebedo", "heber", "febe"], "89": ["Arribada", "barrigrudo", "trrio", "Barriolo", "Physiolo-", "Olo", "T"], "90": ["ayo", "chut", "Sc", "chumlo", "chua"], "91": ["Torto gemet", "Torto", "tort4"], "92": ["Indial", "pcndiam dos\npaineis", "India", "vindima"], "93": ["cubeea", "seeea", "eabeea", "cabeea", "cabeeo d'Avollan"], "94": ["A0", "Go-", "Im", "Go-\nvern Ciil", "Ciil", "Govern Ciil"], "95": ["levantandu", "Santa\nIrcneia", "adeanta", "Santu", "Sonhorio de iSanta", "ic-Santa", "csantdt", "tma", "Infantas", "Santa hereza", "Santa", "Paeo de tSanta", "Nou", "Iuantas"], "96": ["ILLTE LASA DE IYIIHES\ny0", "le luts", "priuo de b", "Lopo de\nlBayio", "petaen de l'ortgul", "lLopo de layao", "uarto de laar"], "97": ["RAMIES", "IYMIES", "Mie", "Ahl", "HYMIES"], "98": ["Jesuina-qe", "Jesuina"], "99": ["Podro", "appeteeer", "apodreeer", "Fnvelheeeram"], "100": ["lishoa", "lILishoa", "Iishoa", "Lishoa", "Lishon", "Hoa", "Pashoa", "I10", "hoa liss"], "101": ["Tallan Ilonra", "Siloneioso", "Ilonra", "Honra", "la Honra", "Ma", "llonra:-e de-\nbrueados", "llonra"], "102": ["Casas", "Balsas", "casas dc\nFranea", "casaes", "Casal Novo", "sohrecasaca"], "103": ["Agasalhem", "salho", "Salzedas", "Alhoius"], "104": ["Billio-\ntheea", "libliothecea", "Billio-"], "105": ["boeirinha", "Vidcirinha", "Virinha", "Vileirinha", "NVidoirinhal Mlas", "Vitcirinha", "Yleirinha", "dirinha", "onta du sobrinha", "0O Yidoirinha."], "106": ["riacho das\nlonas", "riacho das bonas", "Ca", "Peo das Iiehas", "Iachas"], "107": ["Corliy", "Corlya", "Corldor"], "108": ["quatarze", "Chatarizo", "Chatariz", "atarefad"], "109": ["Y ILI.IIII", "tdu", "ILI.II", "ILI.IIIIH CAA"], "110": ["aqli", "Mathildes", "RAMIS\nVoces", "Iamilde", "c1", "Ramilde", "Gramilde"], "111": ["Gies s-", "IIMIIES", "IAIES", "IIES", "RIIES", "RWIIER", "AIIIES", "RMIIES", "IEs-"], "112": ["Iecesvinto", "vintcml", "Into", "Iiccesvinto"], "113": ["Trre", "corredr", "correia\ndum1 latego", "orre", "corredo", "uc uorrera", "Correu", "eorrelor", "U jardim da lorre", "Iorre", "Taorre", "Aorrecido", "Gutiorres", "lorre"], "114": ["Obras Publicas", "publicuva", "Publicn", "I19"], "115": ["anlt0", "va-\nranla", "Airanle", "anles", "Miranle"], "116": ["Ieve", "m beve", "Cleves"], "117": ["qule", "hule", "i", "cvt", "Joqulm"], "118": ["galinete do Cavallcio", "Cavallciro", "Cavallcira", "Cavallcio", "Cavallcirol", "Cavllciro", "Cauvallciro"], "119": ["cuealtnado", "Esgaseado", "tumado", "Acodado", "Itocados", "latejado", "algcmado", "Fado", "ripiado", "ado", "ho sahbbado", "Ajudado", "Ahenoado"], "120": ["mur", "Murtosa", "Mlurtosa"], "121": ["ipressiaonava", "pelu Sud-lxpress", "expressaes", "Sud-lxpress", "oppressi da", "im-\nressionad", "Sud-xpress"], "122": ["Mli", "S. Mligucl", "MlIas", "Mli-"], "123": ["lazenda", "Londa", "Vendas", "ndatms", "Iunda", "pancnda c assuada", "Ninda", "tindar", "hnda"], "124": ["Franga", "d'espcranga", "orangal", "rharanga", "Franziu"], "125": ["rumnotr", "mnodu"], "126": ["Mlinho", "v", "Goncalinhol", "clcalI", "Goucalinho", "Goncalinho", "Gonalinho"], "127": ["Apezar", "leza", "Therezas", "Vcneza", "fortaleza", "nee inglez"], "128": ["bDr", "Mlouaeo", "faeo", "faee", "Iaeo", "baeos"], "129": ["Governo", "inllueneia do Governo", "coniroversia", "vern0", "pclo tGuverno", "ro vernelh", "gaverno", "Gaoverno"], "130": ["conhes", "Sunhes", "conhecidlo", "conhcei", "conheeel", "conhero Men\n3 Il"], "131": ["i sua sbra", "Cc00s", "pelu\nsua goa", "Sua kExe"], "132": ["Iis-", "pa", "Iisfoia", "Troia", "Iistoia"], "133": ["Baro", "Bar-", "baro", "lr"], "134": ["Cenaculo", "Suanches lLucena", "Lcena", "seduceao", "hna lLucena", "Iuceena", "Mlas\nlucena", "ILcena-o\nCireulo", "Lucehna", "Sanchcs Lucena", "Ltcena", "nna Lucena", "Lucena"], "135": ["vlha", "Slha", "bulha co o lr", "lha", "Illha"], "136": ["Ierro", "hezerro", "ferrol", "trror", "You", "lomba d cerro", "cerro"], "137": ["donar", "co ahandonadus", "Abandonada", "bandonar", "Dona-em", "BAnD0", "dcbandou nelo te-\nelado"], "138": ["tanque da\npedra", "Tanque-Velho", "tanqu", "qne u la branquuava"], "139": ["Iigti-", "Iuiigo", "ti-", "Iiga"], "140": ["Iicgcne-", "Iicl", "1r"], "141": ["Iuingo", "doningo", "Domingo", "Dominge", "bomingo", "Torre aos Domingos", "Dom", "Pogo de S. Domingas", "C0"], "142": ["U", "extasi", "Asia", "aSIl0s", "Asia Alenor", "sia"], "143": ["Villar londes", "Novilles", "Villa-Nolhas", "Villico", "Assenbla da Villa", "Villas", "Villalohsos", "Tordesillas", "Villar", "Villalubs", "villas da\ndoaao"], "144": ["Governo Ci", "Is", "Governo Ciyil", "Governo Civil", "Go-\nverno Civil", "tverno Civil do braeue", "Goveno Ci-", "Civil", "Govorno Civil", "Governo Ciil", "Coverno Civil", "Governo Civil-fervera n'elle"], "145": ["mis", "catmisa", "catmpo"], "146": ["Almocei", "Almodovr", "Dr.", "almoo", "almuzem", "almoeo"], "147": ["u S. l", "S. lo-\nmo"], "148": ["qtle", "qtle pctdiu", "tle", "I)o-"], "149": ["Aquella", "Aquellas", "aquella\nvaio ue", "aquella linda", "aquella claridadc", "aquella romantica solidao de\nlenda", "aquella aigagao", "aquell"], "150": ["pclle", "d'clle", "clle", "I02"], "151": ["Seculo", "Seculo das maos tremulas\ndo", "Cc", "seculo xII", "secu"], "152": ["Imnatava", "cimna", "Imnanos", "Imn", "umna"], "153": ["Lento", "lentaenle0", "w len:o", "Lentatnente", "len", "ent ue", "S. lento", "lentu", "Lentro", "alentel", "vent", "lentw", "excellentel"], "154": ["Cuvallo", "Cuvalleir", "triumpho do Cuvalleiru", "Cvalleiru", "Cuvalleciro de Mlalta", "Cuvalleirista", "Cuvalleiro", "Cuvalleire", "tuvalleiro"], "155": ["Ieblte", "elteger", "pr Walter Seolt", "IY"], "156": ["Abhude", "vrdude", "l", "Cidude", "frialdude", "Cidude\nnis axistia nodoa"], "157": ["Villa-Clura", "Vill-Clara", "Villa-\nClara", "Villn-Clara", "YVilla-Clara", "Villa-Clara", "Vocs en Villa-Clara", "Coneelho de Villa-Clara", "ViIla-Clara", "tod0", "iIIa-Clara", "Emn Villa-Clara", "Villa lara", "illa-", "Yilla-Clara", "Yill-Clara", "Villa-\nlara", "Villa-Cla", "Villa-Clava", "la-Clara", "Hljlya-Ca", "VilIa-Clara", "Nilla Clara", "Villa-Clara\nde noite", "Villa-Clara 1 Torrc"], "158": ["verao", "veraculo", "Veras"], "159": ["beus", "beusl", "susl0"], "160": ["xe equcbrara cuni", "abrag0", "braro", "bra0s", "Cibra", "Coibra", "brageo", "Obra", "genebra", "Dbraos", "Coirbra"], "161": ["Mlanria de Crauede", "Crauede", "Craue-"], "162": ["mo", "puc", "Precisamncnte", "otlerecia", "uflereci", "ofiereccr", "etpe"], "163": ["Ilrcileiro potr", "Ilrcileiro"], "164": ["i Torro", "Torr", "Torro illuminira", "ul horrorl\nAtirou", "uo cra\nuI torrio ico", "Torro", "corrodor", "Torroe"], "165": ["1N", "Cntava", "Jricntal", "gritavar:-", "accrescentava", "ce\nempletava", "Ol", "aggolrd\nlcvantavan"], "166": ["olle da orelha", "ponta olle da orelha", "Ir"], "167": ["Governador\nCivil-e", "iovernador Civil, to nr", "Governador Civill Mas", "Governador Civil", "tavernador", "Gavternador Civil du listriceta", "Governador\nCivil", "Governador Civill", "Governador", "Governador Ciil", "tGovernador Ciil", "Governador Civill..."], "168": ["banco de pedra", "baneo de pedra", "ie pedra", "Iy de Pina", "ma revoa-\nda de perdizes orggueu"], "169": ["cureel de guerrd", "Yonge de Cistea", "Mionsieur de Charette", "Pdro de Casiro", "cumisu de chita cir de rosa", "Fx", "tradieiol de desatulhar", "ILLTE cS DE RAMIS", "camadu de raagcns"], "170": ["lheres", "Aleres", "Alfcres-or", "Alferes"], "171": ["mocetdo", "buscear tta", "b-", "torcet", "scet"], "172": ["etroleo", "lEu", "petroleu", "retrocess0", "trolou", "ponetrot"], "173": ["Ienois", "lenois", "Denois", "lenol"], "174": ["Juasi", "t)uasi", "quasi consenti-", "t)uasi inconquistavel", "quasi", "W", "uasi secca", "uUasi", "uasi"], "175": ["desordom", "veridica da desorden", "desorden"], "176": ["Casco", "Cascol", "dmasco", "Uasco"], "177": ["guida", "aida", "Borguinhio", "hane\ncuidadosumentc", "uja", "Iuidas", "Crguidos"], "178": ["Caseo nio so arredava", "Case", "fraseo", "ul\nIraseo", "Caseo"], "179": ["ilLs", "ILLSTIE CA I", "IlL1LLSTII CAS1 IME", "IILLSTIIE", "ILLSTIE", "IILLST CA I AYIIE", "ILLILSTIE", "ILLSTIE CASY ID"], "180": ["II.LLSIIIE CAEA", "II.1.LSE CA1", "II.LYIE"], "181": ["pas-", "as-", "Cas-", "br", "As-", "Ri-", "Ias-", "Bas-"], "182": ["Anarante", "MIirante-e", "Mirante", "imovel\ndcante do", "Mlirante-se", "Violante", "Mirante coo\nsu gorl"], "183": ["tGonclo", "tGon-\nalo", "nclo", "Goncnlo"], "184": ["gratidao", "KE", "tratira", "tirus", "tratira or  me-\nnlino"], "185": ["jale-\nca", "Cale-\ncelhos", "jale-\nus"], "186": ["vizeira gradada", "t]e esvasiira dum trag", "scmpre cnsageira coni", "pocira da lide", "peira da es-", "rcimeira dos\nmnorrioes", "M1", "Tomnada da Bastilha"], "187": ["ste", "homeml kEste", "ste benziam", "revste", "ste\nlongu", "llste lecal", "steu", "ampeuas ste", "Fste"], "188": ["Meret", "teror", "Numerou", "gcmer", "I'erol", "rouba", "Ierozes"], "189": ["Ia", "Assemblc", "Assembleia", "uu ssembla", "Mssembleia", "Asscmbleia"], "190": ["Trez", "Enxarez", "Slarem", "Areos"], "191": ["solidia", "lusidia", "di solide:z.", "idia", "solidao favoravel", "dn s-\nlidio"], "192": ["sorado", "Irados", "Ms", "Rogonerador", "toueador", "gadora", "vrador", "ilha do lmperadorl", "Pccecador", "pomar murado"], "193": ["N1", "pnna de pato", "festa de", "HIisloria de\nIIerculano, o Bolo", "raa de", "tardeta de botes", "iladssia mneza de tcarvalhto", "prcsloza despirilo", "I", "S.", "iddca de artigos", "pera de S. Joaio", "anha de Mlissa"], "194": ["Finta-e", "pelu\ncinta cm affago", "Ainta", "Imnedintaienlle", "EY", "aintda"], "195": ["suflocava", "bcliscava", "mancaval", "Us", "tranquillisar cvocava", "caVa", "santilicava", "Cavado"], "196": ["Aflonsina", "In'ensinava", "Yiya", "cnsinar", "Aansina", "Affonsino", "Affonsina", "Affns", "Affonsinasl", "I8"], "197": ["regoaa", "l'ego", "egoa", "goa", "tegoa"], "198": ["U0", "soltar?-F", "soltarl", "vao soltarl", "voltaris"], "199": ["quarlo", "gaeta d scu quarlo", "Quarta", "csguarlatos", "Iarlo", "bstarlo"], "200": ["ulherio", "Ilhe", "Ulhe", "deseubrulhes"], "201": ["Coim-", "coIml m1", "ecoih", "Coice", "Coimlra", "Uoimra", "im-\nI", "Coim-\nhra"], "202": ["N'esse", "d'essa", "mehor\ndiminiio n'essa", "N'esse tolehto", "N'essa", "cspessa", "lago n'essa", "sessaa ds Cuhtras termi-"], "203": ["mascula", "Cascu", "Cascul"], "204": ["tIma", "setim", "Iolhctim", "Ima", "seim latim", "Estimava"], "205": ["Joio", "Mlana Joio,.mano Joiol", "Joio Brandio", "Joio lIl"], "206": ["Yde", "uao", "uao tcm"], "207": ["balburdia", "d'onde\nsurdia", "ienda surdissen", "surdia"], "208": ["Gstou", "Atastou", "kstoves", "cstou", "kstou", "uvistou", "ji cstou"], "209": ["baix", "baixa cubiga", "dbaixo la\neanal l alti lcvava", "hBaixa"], "210": ["tGuia", "Guiao", "Aguiar"], "211": ["Josopha Pires", "botica\ndo Pires", "bD. Josopha Pires", "sophar"], "212": ["olume", "lumc", "r-"], "213": ["guloss", "Gonulo", "T-(niulos", "Tibulo", "Iidiulos", "qIult", "Iulo", "Iermulo", "Capilulos"], "214": ["Ordonho", "Ordonlo", "Ordonha", "lonha", "Bnrdo", "Aordou", "Atraz o tropcgo Ordonha\ngeiia", "Mordomo-Mlr"], "215": ["IYMIIILS", "ILLITIE CA I IYMIIIE", "IIYMIRH", "So", "IYMIIBES", "io", "IYMIIIE"], "216": ["col umor", "colpadre", "colches", "Colsas", "col", "colu", "coln0", "Iecolheu", "colhi", "Colo-"], "217": ["Casro", "trocass", "Casu", "CAS", "Castlla"], "218": ["Qucm", "lrquc", "Qucrcm", "kE olhe\nquc", "qucm", "quc", "lachequc"], "219": ["Semre", "semre"], "220": ["deia", "Creia", "ouvceia", "bocea cheia", "eeia", "Goueia", "Cundceias", "garygalheia", "Ircneia", "eia", "Ieia"], "221": ["C0rtes", "urte", "Certesa", "Cwrte", "Crtes"], "222": ["Iiguraes", "aeu", "Couraeu", "Couraga", "Centro da Couraea", "huraeo"], "223": ["F", "smhra d", "Hra", "Coimhra", "somhra", "Cimhra"], "224": ["Torrel", "Noolla,-a Torre", "Torre cra ois popularl", "Torre albar-\nran", "Torre est tuito", "i Torre", "Torre reprehendeu", "Torre sen-", "Torras", "elha Torre", "torre da Cmara", "Torre iratada", "Torre conlesso", "Iicillima Torre", "Torre o vyelho", "Torrel lor fi", "Torre", "Torre passira", "Torre ma fallada marailha", "Torre\ncra", "Torreiro", "Torre\nrostituida", "Torre-", "Torre...", "Torre i"], "225": ["cste senhor", "Senhor", "venhora da koa Mlortel", "irna d obe senhaor", "Senhora", "Snhor", "Senhria", "dis\nbtndos senhriucs", "bDeus\nnosso Senhor", "Senhores", "Senhorl", "Tenho", "casa da senhora sua mana..."], "226": ["moc0 osvelto", "emocao", "dcemo au lad0", "eocao", "emogao", "ur"], "227": ["i Casu", "ILLITI CA IE ITMIE", "IL1.STI CA", "ILLITI CASA DE IAMIIE5", "ILLITI", "Y IILL.ITI", "ILLITI CAS"], "228": ["Janeiro", "neiro trayo", "Rio te Janeiro", "jasmineiros"], "229": ["Mlcndo", "tntcndra", "pcndo", "1I", "tcndidol"], "230": ["nna", "Pena", "penna"], "231": ["Pragal", "coragao", "Prau", "Praga", "desgragal", "Iragane", "Ihraganeas", "gragas", "liegencragao", "lragana", "pstna en\npraa"], "232": ["Alem-", "Alemqucr", "Alemtej", "lem-\nbar", "lEm-", "el", "Alem-lordao"], "233": ["Sunches", "Sanches ILucenal", "Sancla", "W'inchester", "Sanches Lucena", "Sanchcs", "Sanches", "Sanchcs ILcenl", "manch0es", "V0s0s", "sanches", "Sanehes"], "234": ["iL.STIE CSA", "LLLSTnE CSA", "U csahto", "jd csti", "I1TIE CNA"], "235": ["reconciliaga", "Concillo de Toledol", "u retconciliachlo"], "236": ["Capella", "lapella", "inlerpelland\ntamlemn", "corisear\nde capellos", "Capellao"], "237": ["Affns de Alhuquerue...", "muralhua", "Quero", "ua", "Alhuquerue", "nrm0u", "Iez"], "238": ["ottra", "Mlagistrattra", "lcttra", "lettra", "oittra\nscut"], "239": ["hitos", "Titosinlo", "Feitosa", "Heitos", "perteitos", "Feitos"], "240": ["lepis", "pisa", "c00", "idealisaa", "hisav0"], "241": ["uannuvia", "vialio", "duvia", "Gouvia", "Doeus Iluvial"], "242": ["HEl-rei UD", "El-rei Iom Alon-", "Hl-rei", "kEl-rei de Leio", "El-Rei - Goncale"], "243": ["Romantce", "Tcso", "estupidissmn0 Santches", "antcs", "ent arantc", "clqantu", "diantc", "Antcs"], "244": ["Mro du ndre", "Antresinho", "Andresinhol", "Londres", "adresinho desbotalo", "Andresinho", "Flandres"], "245": ["Mloguncia", "Provincia", "lulma ancia", "eleguncia", "Venancia"], "246": ["rahna", "pahnn0", "hna"], "247": ["Videirinha", "Videiral Toca", "pu", "Videira", "Videirinln", "Iibeirinh", "Yideirinha...", "Videirinha\ns6 poz", "I\nYideirinha", "Vidceirinha", "Yideirinha", "Nideirinha", "Yideirinha adeantou", "eadeirinha baixa", "Torre Vidveirinha", "Videirinha\ns6", "Videirinlia", "Videirinh"], "248": ["Gracinhn", "Gracinhae", "Gracinha", "Oracinha", "coplaceute de Gracinha", "ILys\ntGracinha", "Cinhra", "nio podia p\nanor le tracinh", "Gracimha", "Gracinhal", "Torre racinha", "Gacinha", "Cracinha", "za dc racinha", "raciha"], "249": ["coa", "LLLLLLLLLLILLLLILLILLLLLLLLLLLLLLLLLILLLLLLLL", "LLLLLLLLLLLLL", "Iit IISllYlllIie \nidraa"], "250": ["IDepois", "Dcpois", "Pois", "Ilepois", "Iepois", "IPois", "lPois", "llepois da hilho", "lcpois", "Ilopois", "lpoi", "lopois", "lepois", "kPois"], "251": ["iaormavat", "pasmava", "Asylo", "recuavan", "sioava", "Levava", "atroava", "SC CUIIS0rVava", "tenlava", "xaVa", "tufava"], "252": ["RE", "Cono", "Lconez", "Congo", "cono", "d'ono", "cono vos d'ave"], "253": ["Sul", "do Sul", "sclprc", "sulprc6a"], "254": ["Sino", "Aflnsinos", "Aiionsinos", "Hnsino", "Ensino"], "255": ["silenei", "ji silen-\nciaosas", "leneol", "silenceio", "sileneia"], "256": ["loa", "Lisloa", "Alloar", "Moloar"], "257": ["N0", "Commo-", "Com-", "comao", "Comt", "tcomo", "com-"], "258": ["iarejando", "greja", "lgrejinha", "Fgreja taio fcia", "Beja"], "259": ["pees de Irecha", "Irecha", "apelrechar"], "260": ["Conselhos do\nBaneo", "Conselheiro", "Nao", "Conselhos do\nBaneo Ilypotluecario:-e"], "261": ["cspada", "Iada", "Iumada", "Boa piadal", "Iiada"], "262": ["Eramn", "Amnbos", "Amninae", "camnisus", "Ilamnejou", "uIamn"], "263": ["eousas vagot", "Cousas", "Usasa", "CSs0s C0usas"], "264": ["Telegralnlnds", "telegrammas", "Telegrapho-ji"], "265": ["Ilereulanos", "Ilereules", "reul0"], "266": ["F\nimmediatlehte", "immdiatamehte", "Immediatamente", "Hirtamente"], "267": ["Iogo", "ogoa", "Pogo"], "268": ["Ilaccida", "felicidade", "Cidade", "Authoridade m'empurrae", "Auctoridade", "earidade", "solemhidade", "Superioridade", "Universidade", "Cidadelhe", "Cidadelhe...", "realidado", "protundidades da\nTartaria", "intiidade d"], "269": ["fresco valle", "valle\nde", "alle", "aqualle", "valle\nda", "Yalle de Josaphat", "valle", "allectuaoso", "allna", "fundo do valle", "calle", "largeza do valle", "valle surde"], "270": ["cohl0", "Ohl", "cohra", "te", "coh", "coho"], "271": ["Inl", "vinlu", "Finlgo", "IInl", "Inl-"], "272": ["Oraea", "ce du raeals", "cmbaraeado", "jograes", "Graeiuha", "Graea"], "273": ["chicotel", "cotm", "csmiucot", "cotmn", "cot", "Cotd"], "274": ["Relhos", "Concelho", "lelhol", "mn velho brazileico", "elhorira l", "Yelho", "Conecelho", "mnoldura\ndo espelho", "Coucelho", "jelho", "Ioeo Yelho", "lelho", "g6da", "vcrmelho", "velhota"], "275": ["Fabica", "Bica-unta", "picad0", "Bicn-Sut", "Bica\nSt", "Bica"], "276": ["Cuiomar de lLandim", "ee", "Landim", "Sandim"], "277": ["sempro reformada", "emprol", "improssiono"], "278": ["Tamhe", "tamhen", "omhebid", "tamhem", "Tamhcm"], "279": ["tquatro annos", "Quatro annusl Assim", "imagel te patrocinia"], "280": ["apradu", "lacr", "restauradu", "lacradu"], "281": ["Pitta", "Pittas"], "282": ["Contrasta", "lu l", "Ioe", "contribioes", "contrira n"], "283": ["ilis", "ilis solta", "civilisuaio", "Ilis-"], "284": ["Iuecna", "Luecna"], "285": ["pasts0", "Choupal", "D", "aschoal", "Paschou"], "286": ["totiu", "juelhs", "Va", "Mtiuel", "Iue", "S. Miguel", "Tuele-"], "287": ["horrifurcmn i prssa", "ji vocemec\ntemn aqtui esta...", "Ordemn", "emn mareha", "pe", "Ordemn Iu-"], "288": ["IIIII\n123\ntm Aor enore", "III", "IIL.LITI  DE ISIIII", "MA I I1IIIIs", "IIIIH\n11", "ILAWIIIINS"], "289": ["Trinoli", "uo", "magnolia", "nolc", "mcninol"], "290": ["alravessar da feuda", "alravez do casaraio", "alravez"], "291": ["JosC", "Jos", "Al", "harpcjos"], "292": ["Santa MIa-\nria da Yarge", "Santa Miaria", "Santa MIaria", "MIaria"], "293": ["suhiam", "suhisst", "suhissult us"], "294": ["pau.n", "pau-\n1"], "295": ["lagar de\nnr", "Couventu de Santa", "Solar de Santa", "eal de Santu", "Senhor de Santa", "Solar de Santa Ircncia-resistente", "depaois de santos", "Enxarez de Sandornin"], "296": ["voss", "vossl", "voss2", "Vosste"], "297": ["grlcvjou eom", "ranjou", "grlcvjou"], "298": ["Iaces barbudas", "momices", "Iaces", "Iace", "face"], "299": ["52I", "IlCt0", "ilcn"], "300": ["pectg0s", "pecs"], "301": ["chamma alta da vela", "chamma", "Cachamita", "faee chammejante"], "302": ["Ilotel Mondeg", "Bo", "Iotel MIondego", "Mlnotel", "es\neutel m"], "303": ["mantd", "romantico", "MIonte-Agra", "sc", "Mante-Agra", "-Ag0r"], "304": ["porcuria", "Naotarios\nda Curia-as resolucnes", "tcuruba", "Clerigo da Curia", "Curia"], "305": ["AIIRE", "Iires", "Rires", "Iresa", "RAIIRR", "lLoureo Iires", "Iaires", "Pires"], "306": ["ba\nnhos", "tm\nnhos"], "307": ["forga dos Ca-", "largueza dos campos", "d'Orgaz", "ceurta ala ds ca-", "Expediao dos Aryodas", "Casa dos Chzes", "tdos pclos", "citna dos teorceis qe se cminat"], "308": ["larr6lo", "Ilarro-\nlos", "k to-\nlos", "Ilarros", "pobre Hlarr0lo", "Barro-\nlo"], "309": ["ulho", "irubulho", "tdi", "Julho", "uSDulhnr", "remergulhou"], "310": ["entere-\ncid c", "Cent0-", "Licenca", "Ceriaente", "Yicente", "dentes;-e", "Nascente"], "311": ["Mlas eu ji sabinl", "Mlas", "Mlas udo", "Mlaseate", "Mlajor"], "312": ["Adail", "Ail", "caIreaIl"], "313": ["ladr uoiro dcve recelr carta dn Preiru", "Mlasteiro", "osteiro\ndo", "Mosteir", "Mosteiro d", "Mosteiro d\nltecadies"], "314": ["Torre\nVagarosalntt", "cigaro", "O0", "Nagarosas", "Nagarosamontc"], "315": ["Ignaci", "Cognae", "Yigny"], "316": ["le1", "lstams", "Tam-\nhem", "tam-\nben ua", "Tam-", "lss c tamusa"], "317": ["Sbelor", "Sahelor", "SUelor", "Sabelor", "S0elor", "eslorgo"], "318": ["balaneado", "Lanea", "Fsses Tanearvilles", "eamurca branea", "melaneholia", "hane", "lanear", "dc\nFranea"], "319": ["Ileeha", "Iles", "Noidles", "noile", "IlES", "losles"], "320": [".Aeto", "phaeton", "ay Trueto-", "Netos"], "321": ["Paorque", "Purque", "Aor", "porque2", "MIarquez de Treiedol"], "322": ["cmmudecera", "ji cspairecera", "Casco emtudecera", "Iesceram"], "323": ["Chegot", "Chega", "Achegou"], "324": ["arvored0s", "arvorcdo", "Iervor", "voreds da qulintn", "d'arvores"], "325": ["saiasita nova", "naqtuella nova", "boa nova", "boa nova de prestes soeeorros"], "326": ["C3A DHE IAMII5\ny", "LTIII N1 IE IAMIIE", "IAMIIHS", "IAMIIYS", "IAMII3", "ILLUSIE CAS5A DE IAMIIIS", "IAMIILS", "IAMIIH5", "IAMII"], "327": ["Mioirama", "Juizo", "Jiggciramente", "Inleiramente", "Prioiramente quiz"], "328": ["Novellia", "vella", "Nwvella", "Naovella", "Novellasinh", "Novellal Co-", "Novellas", "Novellal", "Novella", "nr"], "329": ["melhorira conside-\nravelmente", "Realmentel", "gentel", "latalmentc", "Icalmente\ns6", "Naluralmente"], "330": ["us", "rehentar dum\nmnorteiro", "Sorte inimigal", "Iortes", "Sorte", "Mlunforte", "Norte", "ma iorte", "E8", "Iorte"], "331": ["Aleava", "Alea-\nova", "Alea-", "Aleaide", "Aleagova"], "332": ["Tom-", "Mafoma", "itompo", "tomau", "Toma", "Tomoh", "rctomando"], "333": ["Sangria", "sange...", "tod", "sange"], "334": ["Olho", "volho"], "335": ["valle\nle Canta-Pedra", "Canta-ledra", "Canta-l'e-", "Cahnta-ledra", "Cantapedra", "Canta-l'edra", "Canta-Pedra"], "336": ["XYIII", "IYIII", "xYIII", "YII", "IYIIE"], "337": ["santa\nIreneia", "Cstello de Sana Ireneia", "Aleaova de S.ta Ireneia", "Torre de anta Ireneia", "Santa Ireneial", "Santa Ireneia", "Santa Ieneia", "Snnta Irenela", "santa Ireneia", "Santa Ire-\neia", "Castcllo de Sunta Ireneia", "Santa Ire-\nneia", "Santa Irencla", "Santu Ireneia", "Ireneia", "Sunta Ireneia", "Santa Ireneia Iielmente", "Pacos de Snta Ireneiu", "Santa\nIreneia", "Paeo de tSanta Ireneia"], "338": ["Nosso Se-\nnhor", "to se-\ngu0", "se-\nbes", "te-\nnho", "se-\nnhor", "om alto pu-\nnho", "oa se-\nnhora", "a4pa-\nnhas", "ti-\nnhaca"], "339": ["kFra", "FraIue henet", "Fra", "fra", "Fraaca", "Hgypto"], "340": ["barhacans", "harhacans-0u", "palxa0 de grahdezu\nbarhara"], "341": ["Terreiro da ILouca", "Terreir l ILuuca l", "uerreiro\nmassadol", "Terreiro", "terreiro kF Goncala", "aterre", "lirreiro", "Terreiro da Lou", "chio do Terreiro", "Terreiro da lLoua", "Iusica o\nTerreiro...", "Terreiro aquelle"], "342": ["cscopur", "Ircsco", "copi0-", "apuru"], "343": ["preguica", "Freguezia", "heguino", "seguilra", "preguicavatn"], "344": ["Ceua", "ceuriosidade", "curiosidadc", "sidao"], "345": ["nliou", "Iou", "riso lcnlio", "Fnlio"], "346": ["I1.1 TI", "vozeirio d Tit6", "vozeirio do Tit6", "Iimrio do Gaerno"], "347": ["cou10 ula\nstaca", "Ilbeiiula", "UCrisnula", "Populaea", "Denuladot", "pupula", "ula", "co ula"], "348": ["Bra-\nvaes", "IBra-\nvaes"], "349": ["taio tina in-\ntelligeucla", "Intelligencia", "inlelligencia", "1F'ul-\ngencio", "Brxas"], "350": ["Mos-", "Wamos", "agaa limosa", "Iumos", "Famosa", "ma teimosu", "Mos", "Jantimos", "Viemos"], "351": ["icha", "Er", "Orcha", "chao", "Juuhao", "oa"], "352": ["Ai per-\ndaio", "jar-\ndi", "I'ar-", "Bomjar-\ndimt"], "353": ["Mlarqu0s", "Mlarte", "laria", "Mlaria da tGraea", "Mlaria", "Cavallaria", "Ave-Mlaria", "Mlarqucz do lancio"], "354": ["scu eoraao:", "dAmor", "cxclamou", "utr'ora", "Zamora", "oraia"], "355": ["Alvaralhao", "Alvari", "Alvaralhio", "hio", "alvejaral"], "356": ["tambcm", "Tambom", "tambel", "Tambe nio", "ambem", "Tambetm", "Tambe", "tambom", "tcu"], "357": ["Ientre", "Pntria", "entrrdo", "C-ntr", "Sntr"], "358": ["aeabar", "Aeaba", "abangie", "eabide"], "359": ["con-", "Oon-", "turor con-\ntra", "Con-"], "360": ["Archio", "tmna cabana", "Poro da Covilhan", "fundad 1o\nanaes da sua Casa", "Archivo da Casa", "tda casal", "Iiscnrso da Coroa"], "361": ["Tili", "d\ntili", "Til6", "tutiliares"], "362": ["Tructe-", "Tructesindo", "Trctesindo", "nto Tructesinudo", "Iructasindo", "Tructcsindo", "Tructesintol\nConfiae", "Tretesinio", "Tructezindo", "Tructesino", "Tructesinudo", "Iructesindo", "Tructezindu", "Tructesindu"], "363": ["quanda", "quand0", "Quan-", "quanda\nsoubo qule", "quantdto tell ac-e", "Hoi  allivio quand", "quanda\nl", "rcuand", "Quand", "raca larrolia-quando om baixo", "uando"], "364": ["calore", "l'ore", "lore", "Anto-\ninho loreuo", "Ilorete", "Ilores"], "365": ["Ulivcira", "C0I0", "Olivcira", "d'Olivcira", "Olivcira?"], "366": ["Voees", "voei", "soeeggo"], "367": ["Europa", "Iururou", "dUuro", "Furopa", "iuror", "Futuro"], "368": ["1I\ncete", "ete", "retesudas", "Chete"], "369": ["ctmrehendia", "Comprira", "comphend", "hehendu", "resoantesl \nrcahnente uma comprehensao tio segura", "comprehendia", "Iepreheusio"], "370": ["Circulos", "Circulo", "Eleitoraes do Circulo", "Vim"], "371": ["Barrlos", "llarrlo", "Palacete dos fidalguissimos HBarrlos", "Brrlo", "Iarrlo", "Barrlo", "abrao do 3urrlo"], "372": ["Cavalloiro", "Cavalloira", "avalloiru", "Caalloiro Niol"], "373": ["beputadol", "Tado", "u dos\nsilios decantados", "Coitado", "dep- \ntadon", "Estado", "Affoutado"], "374": ["uIla", "Iilas", "Ilas", "Froylas", "us dtns manas\nparlas", "YV", "vilan", "halas"], "375": ["Casa illustrce", "ILLUSTRE", "ltstre"], "376": ["Eleicio", "afan da Fleicio-para", "Fleicio", "Eleiciol Pois", "Eleiciol", "Oposicio", "pudicicia", "Eleico"], "377": ["Iesnada", "Nadal", "uas mesnadas", "Inadava"], "378": ["higodeira megra", "bigoleira", "biggode", "bigodc", "airavez da bigodeira", "bigodeira", "N6s"], "379": ["burbudo", "mudruguda", "veuda", "buda"], "380": ["Fildalgo", "idalgo", "iidalgo.- l", "iidalgo.-", "Nidalgo", "Widalgo", "Nvidales", "Fialgo", "tidalgo", "lidalgo"], "381": ["cemiterio", "Cemiterio", "Nli\nnisterios"], "382": ["Litteratura", "tartura ji", "littwratura", "Naturalmcnte", "Littcratura"], "383": ["Cheles", "Chel-", "Mleles"], "384": ["dubravu", "avor", "Bravo", "t", "brav0", "bravio", "bravol", "Bravol"], "385": ["alargne", "l.arg", "FE", "Invento-\nres alargavai", "largu", "Largo", "largs", "alargne\nform", "largulea"], "386": ["Coronel Iraneoso", "banet-0", "baneo d'entrade", "Mraneo", "baneo", "loneo"], "387": ["Casitira", "Casira", "SimI", "Casimiras", "Cusimira", "casimira"], "388": ["janellinha", "jnnella\nerra", "luas janellas", "Ilanella", "i janella", "lesconflado das\njanellas decrepitas", "canellas"], "389": ["io passcio", "Aostcio", "mcio", "Malluciou", "si-\nlencio", "atd aprccio"], "390": ["Craquede:-aS6", "Craquede", "Craquede:-aS6 sta"], "391": ["rua Yelha", "ViIla-Velhas", "Bic-Yelha", "pa-\nrelha", "Yelha", "om"], "392": ["rins", "kE", "mrInrT", "0O", "RsInS"], "393": ["venida", "Uni-", "lBruno", "brunida"], "394": ["segtnda porta", "frouxidio da porla", "bom Joio da Porta-a", "bom Joio da Porta-a qus"], "395": ["Cundidato", "fundia", "a1 paixii profund", "n0 fundo"], "396": ["Fnu-\nlno", "k pu-\nlu", "clno"], "397": ["mcxcriquice", "Ilnrique", "MIoeambique", "Ilenriqurcs\nAhalou", "toriquete", "Manrique"], "398": ["Mlalta", "lta", "loi ompnnlta  pians", "Pilta", "ksfaltato"], "399": ["Cimbra", "Coimbrn", "Coimbra", "Loimbra", "oimbra", "Coimbra\ntcem", "Bispo de Coimbra", "Cuimbra", "Coimba"], "400": ["Alcaide", "I\nPcae", "trno dn Alcaeova", "Alcaeova", "Alcagova", "Alcaova"], "401": ["Franciseo", "kFranca", "Franca", "Iancas", "Rei de kFrancal", "Iranca", "tlia lanca", "sedinha branca", "Mranco"], "402": ["sa-\ncudindo", "Ieindo", "Truetcsindo", "gruhindo", "Iructczindo Iamircs", "Iugindo"], "403": ["polr", "Tu", "Polas", "cacarolas", "lngge", "iolau", "esmolat pr"], "404": ["Cortlor", "Cortcs", "Cortaor"], "405": ["d'Ullma", "Ullmar", "coI ulla", "ulld"], "406": ["Grande", "Grande Ilonda", "Poco grande", "Tanque-Grande", "portao grande", "sen grande\nliomance", "MIande", "mn grande", "grandc"], "407": ["Ciyil", "Gavonador\nCiyil", "Ciyis", "Yil"], "408": ["Fntio", "Entio", "sangue.- Entio", "senti-", "Ienti-\ndio", "Mls", "kntio"], "409": ["Ioreto", "Ior", "lx", "Mlalchior", "Iorfual"], "410": ["IRYMIlIEi", "umilia'", "reeoniliaeio", "familia", "muhilia"], "411": ["Gzet lo Irlo", "Sev-", "Gzet", "Quamlo Ics"], "412": ["lamina d'estanho", "Pestana", "d'estanho", "Constantinopla", "tos de cstanho"], "413": ["Scvcrosa", "5I\norosa", "roshaal", "kRosa", "Temerosa", "Rosa"], "414": ["Corvello", "Tello", "Leanlro  Bello", "ello", "Iacil de rellorir...", "Tordezello", "licbello cxiste", "ehlaga nm tornzello", "Velloda", "Re-\nbellos", "Mindello", "murxzello\nimovel"], "415": ["eino\npopularisuala", "n0 sual'al", "suala"], "416": ["conlo", "conlra", "conlirmou", "sc senlra", "Onlram"], "417": ["Gragea", "meigra", "nogra", "sesseta grausl\nN", "Agra", "Graal\nIla", "ygrades", "cova negra", "Gra-", "Graa"], "418": ["Naio", "Ir-\nnai", "naio estavaos", "nai\nstci", "naio", "nai\nuzSSe"], "419": ["Seeretario Geral", "secret0", "Secretario Geral", "Secretnria", "Secretaria", "Vigario Geral"], "420": ["om camisa", "Caminha", "Caminho de Ferro", "ca-\nminho", "mnc cminho", "Caminho", "pergaminhh\nluro"], "421": ["Mladeira", "Salgadeira", "ladeira de S. ento", "Iadeircnta", "ID"], "422": ["Nio", "ntonio", "mnio", "Inios", "nio\ns6", "deixo2 Nio", "Bntol Nio", "nio", "Novecenios"], "423": ["lPocmeto do tio\nluarte", "Poeueto do tia Duartel", "Ioemneto do Tia luarte", "Nu", "Ioemela do Tio uartc"], "424": ["paru ci", "Pari", "Paris", "lPar", "laru", "paru"], "425": ["homcm", "homcn1", "Toe"], "426": ["Louredo", "ILourengeo-em", "Loureeo", "lour", "ILourenal", "Lourenco", "Lourenca", "Lourenc", "louyor"], "427": ["Paio Ramires\nPe", "bazio dos liamires", "raca\ndos liamires lcpois", "Paio Ramires", "Ramiros", "uIl\nHlamires", "Ramires", "IMIRE", "Remires\nEsi", "Mlen-\ndes Ramires", "Imires", "Ramiresl", "Hlamires", "Ramires- licando", "liamires largal", "Rami-", "Viconte Iamires", "Iamires", "aOh Ramires"], "428": ["lages", "Algurve", "Alges", "lolge", "pelgei"], "429": ["Fidalgo da\nTorre", "aFlor da Tren", "Fidalgo da Torre", "Fidalgo la Torre", "Fidalgo da lorre", "Fidalgo da orro", "Fidalgo du Torre", "Fidalgo da Torro", "Fidalgo da\nTore", "Fidalgoa\nla Torre", "Fidalgo reclhendo i Torro", "Fidalgu da Torre", "Fidalgo da\nTorre cra", "Fidalgo da Torre\ncoIn risonll0"], "430": ["acreditol", "acredito n'esses", "Crede", "aeredita"], "431": ["Condudo Portu-\ncalense", "tdo pepin0", "Condudo Portu-"], "432": ["pergaminlo", "mlml", "vergastu", "vergel", "vergatdo"], "433": ["Rosinha", "gallinha cosida", "Iranguinha", "Ininha", "miosinha da Snr", "linha varunil e scmpre", "sinha"], "434": ["aquete Iorl", "jaquetn", "jaquetia"], "435": ["nma", "lnma"], "436": ["L-\nci", "Yue", "ra-\ncinha", "Gra-\ncinha", ".Noti-\ncis"], "437": ["CTeatua\ncoo ellal", "cautclla dum", "ellae", "bclla tazen-\nla", "vivem I'ella", "hella 10", "bella mulher", "Yella", "la r0xa", "lla uanli", "llanella azul", "u(uella martcha", "Noella", "du\nI'ella", "ulla patadu"], "438": ["u roponte n'ossa", "ponla", "Ponte", "Ilontem", "Ponte...", "d ponte"], "439": ["larica cscura", "cavallarica", "Atrica", "larica", "Ihetorica", "Mlaricas"], "440": ["baiso", "Lisoa", "Lisoal", "pn", "Iso"], "441": ["C1 UI1 hu Claro", "deelaro", "dcclaro", "ViIa-\nClara", "pcla", "declaraia", "T16", "Yde este Claro-Sol", "Claro-Sol", "claraao da ftorja", "Clao-ol"], "442": ["Coio", "Croio", "Ioio", "Ioi", "loio"], "443": ["Pacos de Severim", "langas de calnisa", "Ionge", "Apcnas de Ionge"], "444": ["Feilosa", "loche azul la eilos", "peilo", "Feilos", "Philosoplios", "losa", "llosa", "Ieilosa", "Ilosa"], "445": ["amargradu", "Iiz", "margeIm", "Margcs"], "446": ["Calcadinha", "Caladinha", "coborto dc riscadinho", "a\nCalcadinha", "Calcadinha de\nYill-Clara", "botoes das\ncalcas", "Calcadinha\nle Nilla-Clural", "Cnlcadinha", "Y0"], "447": ["pertmar as\nmnos", "Mlertola", "Iilerto", "llc pertnne-\ni eamo m", "Perto", "mrto", "espertol", "I(6"], "448": ["Fllc", "ellce", "ellc", "Ellc"], "449": [".-MIas", "MIas", "Mias", "MIa-", "Ias", "dc"], "450": ["us lns d'Aggsto", "optia er ar-", "dynastia d'Aviz", "Dynastias"], "451": ["Colonia", "visiahanca da llosa", "idonia", "Colonia da lotiea", "ajudania da losa", "I1ou"], "452": ["Giar", "Irgia"], "453": ["Iulito", "Paulitieal", "litotl"], "454": ["Semanario", "canar", "nar", "canaviaes"], "455": ["I,1.ITII", "TiI6...", "II.ILTII", "IIL.LITIIE", "Nyha", "Tii"], "456": ["sel", "ba", "sel\ntsse", "tel\ntant0"], "457": ["grduch", "horoieos", "hordu", "Jordde", "imni\ngorda", "corduas"], "458": ["u MIralo da llerva", "herva", "jurtira reserva", "hervaeal"], "459": ["Justiga", "atiga", "justoln", "Justica", "justificaya", "Justinu"], "460": ["collegio de S. ilt", "Iolle", "molle", "sailro\niolle", "collete", "olle", "Mlolle"], "461": ["jardim rcgado", "Ohrigado", "Obrigado", "ohrigado", "Mns", "Pohre"], "462": ["rioso", "Iosa", "re-\ntezou turiosamente", "Iahoriosanwnte", "furiosment", "Ariosa", "liosa", "kiosa.-", "Riosl", "Iiosa", "Riosa"], "463": ["Yidainhos", "vidae", "Vidainhos"], "464": ["Rio-Mlanso", "io-Mlanso", "Visconde de Rio-Mlanso", "llio-Mlan-\nso", "lio-Mlanso"], "465": ["Remarigcs", "Inuncaria", "Inontaria", "cspalhaia ramaria das faias", "Alugaria", "Imaria", "marid0", "ucharia"], "466": ["Cruz", "Cruzeirol", "Mmniciro", "Cruzciro", "lomba do outciro"], "467": ["pessonl", "Crisola", "sia risonha", "Ias risohos", "s0rriso-em", "risonll0", "Nll"], "468": ["tardaneea", "Hastardo b-\nI1aa", "tardlas", "dy fastaru", "Bastardo", "Vasta", "Mastard\nacautelladamento", "lBastardo", "Iastardo"], "469": ["tque", "quel eImnpurra", "roquel", "brotquel"], "470": ["Tempos", "temp"], "471": ["bahu", "Mestrc:-al", "Mlestrc", "Mlesmo", "Mlestrc do Templo-a"], "472": ["Pereira da Riosa", "Preiru", "Iereira", "Pereiral", "Pereira Brazileiro", "I'ereira", "Pereira...", "Pereira amigol", "Carreira", "Mlanoel Pereira", "Pereira", "ji u lPereira"], "473": ["Palacio", "Palaceete", "Palaeete", "Palaeete inaccessivel", "Palacete"], "474": ["Mlont-mr--", "Mlontemor", "Sn", "Mlon-", "Mlont-mr-- ji", "Mlonarchia"], "475": ["Teixedo", "Treixeda", "Trcixedo", "Treixedo", "Treixelol", "TreixCdo", "Troixedo", "Marquez do\nTreixedo", "Treixedu"], "476": ["Gutiertes", "UTIE", "Gutier-", "Gutierres", "Guticrres"], "477": ["Mloscatel", "tosca1", "toscard0s"], "478": ["effusoes", "oesti", "phas seis infancoes", "Yoes", "Fr1", "pcoes"], "479": ["at casa do legedor", "II.IyRTIE CASA D IIAIES", "casa das louzudas...", "ILLST CASA DE AInE", "pr casa dae"], "480": ["us chi-\nmellas", "Chellas", "Vellas", "N'llas", "rua ds Yoellas", "Cellas l ull", "Cellas", "bagatellas"], "481": ["pas-\nsado", "pas-\nsls semanas", "m pas-\nsadico dc travcs", "elo e-\nsadamonto", "lampcjos ro-\nsados", "pas-\nsear", "as-\nsobiava", "Pas-\nsado"], "482": ["Ctec", "Iancte", "Yocts", "lEscutel Yoceecte", "Yocte", "Escte"], "483": ["Pintainha", "Pintainho", "Pintai-\nnho enfiado", "Pintainhan", "Iainha", "Grainha"], "484": ["traternal", "perna manca", "arnas", "goWernaa", "tahberna"], "485": ["primno", "Primo", "Primvera", "ue primorl So6", "opprime"], "486": ["Castello de tSanta lreneia", "Santa lrenecia", "Sonhorio de iSanta lreneia", "Santa lIre-\nneia ...", "Santa lreneia", "castello de Santa lreneia", "Tor de Santa lreneia", "Santa lrcneia"], "487": ["Nenhm", "Venha", "Nenhumal", "nenhua", "Nenhma"], "488": ["ucles", "Simples", "Truclesiudo", "Io", "chcle", "Auclor"], "489": ["postiga du barbacan", "harba", "barbacan", "arbacan", "cirado da arbacan", "portello das harbacans", "Oh"], "490": ["Canellia", "Taholliao", "repellia", "Iamlliar", "imellia", "d'alliana"], "491": ["re-", "Re-"], "492": ["ILI.LYTI", "3I", "ma", "sel IuIlII Ile uelra", "IuIlII", "Philippes", "IILILITIE", "Ili", "Eilim"], "493": ["Pretas", "cts pretas"], "494": ["Fingimento", "Poento", "Inento", "Iuento", "Bentu", "Bentol", "novecentoste\ncineoenta", "a3", "Hento", "Bento", "Iento", "mnhento", "Bente"], "495": ["Obriga-", "rapuriga coi ri0s", "Vigas", "llymn0", "Wriga"], "496": ["onze ti-\nras", "arriei-\nros", "Oliyei-\nra"], "497": ["t1\nserredo", "d'alm serras", "icrras", "Serras"], "498": ["sortel", "tortel", "Portella", "portello", "lortella"], "499": ["J0ao\nGouveia", "Geuveia", "Gouveia", "ouveia7 Ve", "Ceuveio", "Gouveialn-", "Josd Gouveia\nji"], "500": ["scgo", "Ncgocios", "ancioso", "Deliciosos"], "501": ["ceitcei", "cceie", "Succedeu", "yez\nue succeda"], "502": ["Val-", "Hilal", "filalgas", "Ilalsuas", "Filal-"], "503": ["nala teinia", "vein", "geinia", "bein", "eIn"], "504": ["amhus", "luzia ut", "Imu", "Zamhczia"], "505": ["cOco", "cocertur", "Paroce", "Coce", "Socega", "Noce", "Yoce"], "506": ["cristes", "tristeza", "triste:-", "Cister", "eom tristeza", "iriste"], "507": ["Lentro lgeneradotr", "Ie-\ngeneradores", "Ilegeneradores", "Ie-\ngcucradores", "Ie-\ngeneradores realisassem", "IIistoricos \nIegeneradores"], "508": ["klle", "vlle", "Hlle", "lleeehedria", "lle", "Zlle", "aqulle", "Flle", "lLei", "llle"], "509": ["Louzadas", "Louzadasl", "I.uuzadas"], "510": ["chi", "zeviche", "Chiche"], "511": ["Mlatheus", "Iiel Mlatheus", "HEu", "Mlathilds"], "512": ["vicu", "adelgaca", "Acadeicu", "Cadeia"], "513": ["Inil", "Adinislrao", "Mlinistro", "aMinistro aeceiltz", "Ministerio dn Fazenda", "Ministro", "Administracao", "Mlinistro das Oras", "Administralon\nresutiu a sua idda", "Nis"], "514": ["ciencias ociaes", "amcias", "ccia", "Con-\nsciencia", "Iaee", "maledicencias", "cnveniencia", "Currepolencias", "Ias l"], "515": ["Poemneto", "Bnrdo o Poemeto", "Poemelo", "Poemeto"], "516": ["Principes da Christandade", "Christo", "Christs", "Christaos", "Christais", "Christovan", "Egreja de S. Christovo"], "517": ["Ioutor", "bou", "Doutor", "Outulrt", "loutor", "r.\nboutor", "outorl"], "518": ["elle", "aruelle", "d'elle", "Yelleia", "bellez", "Ellei", "l'elle", "fazeer delle u", "cellencia", "kElle", "cancelle\ndo", "ropte para elle", "n'elle", "Yelleda"], "519": ["ji n-", "I N0", "ji ovwral", "ji elo", "CS.-"], "520": ["encolhera us hombrus", "ttso", "tsombra", "desombrggador"], "521": ["Freixos", "hixos d'cssas", "Freixomil", "freixos pcla bcira do ria-\n1", "Viseonde de reixonil"], "522": ["Tejo", "Alemtejo", "Alcmtejo", "Alumtejo", "Vejo"], "523": ["Hlihecira do Coice", "alvoraeo co\nue", "cco co", "taio corto", "riseaudo co0t", "Lpo con"], "524": ["chcgada", "Ilamueente", "rasgadamuente", "mueu", "Iolgadamente", "Fuente-Guihal"], "525": ["agoa do\ngo", "ygOja", "loja do\nliamos"], "526": ["Joio Gouvcia", "loio ouvcia", "loio Gouvcia", "Gouvcia"], "527": ["Burrnlo", "junlo", "mnonlo", "senlo", "cnnlo", "innlo"], "528": ["Mlendes Ilami-\nres", "pendes", "Gonalo Mlendes\nHamires", "Mlendes Ramiresl...", "Mlendes Iiaires", "Mlendes\nRamnires", "Gongcalo Mlendes", "Mcndes", "Mlendes de Suuza", "Mlendes", "alo Mlvendes", "dependessc"], "529": ["lraco", "caracolando", "raco", "Iraco"], "530": ["tque montasste", "monte c vualle", "contevo", "Montemor", "Monte", "Montcmor", "desontelra", "monte", "Yivamontc"], "531": ["Vezes", "lezembro", "Iezembro", "Setembro", "Novembro"], "532": ["Ieonel", "Leoneses", "Synonieo"], "533": ["Iaio", "Maio", "Mlaio", "Bayaiot", "taio", "1E"], "534": ["commette", "ul", "mettc", "mettia", "metteu"], "535": ["Acaha", "cahe", "acahar"], "536": ["iruio", "huio", "esguio", "Aprlo de\nuio", "I. Guionur", "eluio", "uuio"], "537": ["Cintra", "caontra", "Cintra\nIl"], "538": ["Vo-", "utr seuhor", "Cuseo", "Museu", "crepuseulo"], "539": ["csada arrastanl", "arraial seguro", "l'Arraz", "aularrad", "tore albarra", "arranue"], "540": ["Garcia", "l. Garcia", "lorcia", "CUIII\nGarcia Niegas"], "541": ["nIna", "Iina", "China", "Ua\npcrna divinal", "ra-\npina", "ueiinad0s", "Ina", "Inais", "lina", "tinal"], "542": ["Gela", "Luela", "lEls", "Icela", "ua\ntssidela", "lela", "illlela carta", "Gzela"], "543": ["Yolvesscm", "Silves", "essc"], "544": ["Iogar", "a4\nrcgar", "Clgarr", "u Clgarr", "agarrcu"], "545": ["Ahos", "Ambhos", "ambs", "mehos", "us puhhos"], "546": ["aspreza", "spre affavel", "schnpre", "seupre", "serpre", "pre", "esquego sepre", "sepre", "selnpre", "k\npre"], "547": ["Oliveira de bae dad0 col", "Oliveira-no\ndosejo", "Oliveira-", "Inlependete d'llveira", "Dliveira", "d'Olveira", "d'Oliveira", "liveira", "Oliveiral", "Iliveira", "Oliveirat", "Uliveira", "Oliveira-no", "Oliveira", "Im Oliveira", "Olivyeira"], "548": ["nanhava", "tnanhal", "t nanh", "banhala", "phal", "aanhar", "Noruhal"], "549": ["eom requeada", "Mlacheque", "pequen0s", "requehro", "Ns", "pequerrueha tao", "pequchiha"], "550": ["inlluencia ce", "inlluencia d'outru home", "lLueena"], "551": ["Corresondencia vin-", "Carrespondenaia", "Correspndencia", "conlidencia"], "552": ["Vo-\ntos", "Bcn-\nto", "Vatos", "ro"], "553": ["bbia", "stbia"], "554": ["Catharina da Russia", "lussia", "Hussia", "Iussia", "Atlus", "Yuss"], "555": ["Portugueza...", "tugga", "alPortugal", "vclho\nlortugal", "I'ortugal", "Pwrtugal", "lPortu-\ngal", "Portugal\nEspantado", "velhu Portugal", "Intantas de Portugal", "vulgurisar Portugal", "lortugalsiuho", "lPortugal", "ortugal", "Portugal-", "Portugal\nTerrs", "lortugal", "Portugul", "Portugal", "Portughl", "Portuguc-\nzest", "Partugal", "Iei de Portugal"], "556": ["la Pharmacia", "Iharmacia", "Maciel", "lPharmacia", "es padacia", "harmonlia"], "557": ["desolagio", "I'is", "desolado:-"], "558": ["Arinda", "Cwrinde", "Curinde", "Corinde"], "559": ["hndr", "Alexandrc", "Andrc", "Andre", "Mndrc"], "560": ["d'Africa", "Africn", "Africa", "i Africa", "Africal", "Africa degredadol Jesus"], "561": ["fornt", "jornaes", "Annaes", "f5nr", "jornacsl"], "562": ["Ate", "Iatedo", "pateo-", "Iieatei", "Ctate", "N'm", "Mateu"], "563": ["vivondo\nn'estes silios", "ste par-", "d'este Pego", "Pego", "histria d'este Pego"], "564": ["Solre", "solueou", "Soledl", "solurnu", "Sol", "solb"], "565": ["Goncalo", "tioncalo", "Goncal", "Goncalo Iami-", "Concalo", "Goncale", "Goncale\nrovivia", "toncale", "Entao Goncalo", "Goncalo-colno", "Goncale\nn'um rijo abraco", "grilou Goncalo", "Goncalio", "Goncale\ncsfregou", "IYMIIHS\nGoncalo", "louvadol\nF Goncalo", "Goncalo Ia-\nires", "g)aa", "Guncalo"], "566": ["Solretudo", "sobretud ra", "sobetudo", "destudo", "etu", "sohretudo"], "567": ["sc lcvntasse", "Assem-", "Asseblca", "Assemhleia tda", "Assemhlia", "Assemhleia"], "568": ["heaso", "espinguarda", "cuapc dc daso", "guardasolinho", "guardasoes", "uarda p0"], "569": ["anssim iucia", "lindissimo", "avisu", "preciusissimo", "Iravissimo", "avisira", "Bravissimo"], "570": ["pur\naqucll lanee", "aaquclle", "Aqucllas", "Novclla", "ue", "Iaquclla", "aquclla noltc de Castollo"], "571": ["Iitol", "Iiti", "Iit6", "Iit"], "572": ["Setiaes", "Quaes", "teclaes", "Ilrayaes", "Ficaes", "aes", "Ribadaes", "JD", "Waes", "paesl"], "573": ["risnho", "Jlunho", "Junho"], "574": ["eiradu", "meir", "aJueira", "ocheira", "Cerqueira", "Terceira", "Esgueira", "Uliyeira", "Ccrqueira", "reeheira\nde Mithologgia", "uei", "poeira;-e"], "575": ["penteaya", "hntea", "ntntea", "I)eunte", "IL"], "576": ["tuto", "Sinuto", "jnuto", "Iuto", "Iutos"], "577": ["uas ideas", "lDuas", "uas", "uasl", "hlss", "l)es"], "578": ["Ig0", "gallinhaca\ndinheiro", "Pinheiro", "butarinheiro", "souto de azinheiros"], "579": ["lionadn", "Nacional", "Nacionaes", "Nacio", "Proprios Nacionaes", "Lionala", "Bibliotheca nacional"], "580": ["--16 Corimle", "porim", "Corin-\nde", "miml om", "Corimle", "iml", "Corinle"], "581": ["homhro", "Chro-", "qte ahro", "Se-\nteuhro", "ehro"], "582": ["Nerenos", "nossna", "Nosse", "Sr", "Yosses"], "583": ["Mlieira", "Olieira", "hieira", "flieira", "l'Olieira", "Oiieira", "d'Olieira", "Polieia"], "584": ["llayio", "eoxn", "Buyio", "Hayio", "ayio"], "585": ["senllor", "lloutr", "lloma", "lLop0", "Gallo", "lloe"], "586": ["Nunes", "Nunen", "Nes-"], "587": ["llotel Central", "po", "mi", "Iotel", "Central", "Iotel Central"], "588": ["paranda", "ba varanda", "leante dessa varanda", "aranda", "varandal", "Mirandal", "pedra da varanda", "reburda da varanda", "Jaranlin", "randa", "i varanda", "mandaran", "procuranda", "varanda po"], "589": ["luy carpinteiro", "uuteiru", "inteirira", "inteir"], "590": ["IL.1.STH", "IL.1", "IL.LSIE"], "591": ["Cunhaesl\nLi", "Cunhau", "Cunhas", "varands dos Cunhaes", "Curhaes", "unhaes1", "Cu-\nnhaes", "Cunhacs", "Cnhaes", "Cnhaeste", "Cunhaes", "c-"], "592": ["uem", "iremnia", "Quemn"], "593": ["tiro", "quairo", "iroya", "Ioiro", "Iros-", "iroar", "ale oulro retiro"], "594": ["Alcacova", "Alcacer", "Alcacva", "aceri"], "595": ["pe-\nueno", "pe-\nquenol", "pe-"], "596": ["ILLlTIE", "ILLTII CA1", "IALLTI", "ILLTIE", "ILLLTIE LLAA"], "597": ["clueaco", "aco", "Maco", "Paco", "Nacojas", "acorcuva", "Faco", "tum pataco", "Mel-\ngaco", "Acor"], "598": ["orli", "historlia da bulha", "orli qt"], "599": ["quom", "Tabacaria", "Ca-", "Tabaca-"], "600": ["n'ult", "Una", "n'una"], "601": ["Iloin", "Ilojc", "ilorir", "Ilor", "Ilo", "grilou", "ILouatasl"], "602": ["Ilistoric", "Iistorin da\nttminisreo 1'nbliz", "Iistoria", "Ilraz Victorin", "Ilistoria", "d'Ilistoria", "Hlistoria"], "603": ["Caramnba", "carambal", "Caramha", "fcitol Caramba", "Caramba", "earamba", "caralba", "ce"], "604": ["neeessitandu", "necessitoa", "Necessito"], "605": ["Valrerde", "Alre", "Ilres", "Enlre", "alr cupos", "Alril"], "606": ["InCm1 InrUnCuS", "InrUnCuS"], "607": ["Hiscnia", "cni", "scn"], "608": ["Ladeado", "Mleia-lade", "mao inquiela", "proprielade", "Pielade"], "609": ["loj...", "Sao pecegos...", "g0", "us pcs...", "Sao"], "610": ["ILISTIE CASA", "ILLISTIE", "UTIE CAA", "ILISTI", "ILILISTIE", "IILILETIE CASA", "ILILISTIE CA", "chisti", "IILILSII CAA"], "611": ["noido", "tencolhidu", "Ie", "Cnlhido", "clhido"], "612": ["Obhi-", "Ophir", "Phi-"], "613": ["Tomeario", "Temerario i Carlos", "litlerario", "Temerario"], "614": ["IMIHES", "Tahes", "la Hes-", "I13", "IMI", "Imie", "Ihe"], "615": ["lEra", "dis\nsera", "elera d", "Intoleravel", "Colera"], "616": ["Iolitica\nute o0 oncalo", "Politicos", "Politica\nkElla", "Polltica", "luliticu", "Politica", "lolitica", "botica"], "617": ["Mendonca -anbos\ncomn parabens", "Comno", "comn", "paro\ncomn", "Comn", "comn cognae", "comn roiuantic0\ngarho"], "618": ["u marmore do lavatrio", "Patriotisuo", "Cu urtrio", "lmperatriz"], "619": ["d'Aflonso Gomes", "consolad", "AfIonso", "AIlonso Y", "Atfonso", "consontia"], "620": ["transpoz", "transvira", "Trans-", "Trans-\nvaal"], "621": ["Mul-csala", "prala", "Alalou", "saladu", "Ala-do", "Natlal", "Alal"], "622": ["Nisconde", "Yisconde", "condemnando", "Yiscounde"], "623": ["AhI", "Cahio", "RE\nahi", "trahid rmmec", "Ahi", "ahi"], "624": ["hiqucia das otas", "rua das Ptgas", "rua d rinceza l. nelia ati", "rua das\nTeeedeiras", "Ptgas", "rua das Vendas", "velta das onze", "rua das leccdairas"], "625": ["Hem", "ontade", "Vontade hem\nexorcida"], "626": ["Mlendo de IBriteiros", "Mlendcs", "Mlendigo", "Mlendonca", "Mlendongcas", "Mlen-", "Mlaria Mlendonea", "d'omle", "Moendo aes", "Lenda", "Mlendo de IBrieiros", "Mlendo", "Mlen-\ndoncas", "capitaao\nMlendouea"], "627": ["talhla", "Matalhas de Napoicao", "Iatal", "Natal", "Matalhas"], "628": ["Oh Avs", "n Snr", "--Oh Snr"], "629": ["lidalga", "Fidalg", "Fidalguia", "fidlgus", "idalgro", "Fidalg\nconsenliu", "Fidalga", "Fidalo", "grituu o Fidalgo", "zs", "Fidalgo", "kFidal-\ngo"], "630": ["aterrado", "perra", "Terra", "terraco do jardim", "Terrciro", "Ierra", "terraeo", "terrugens saobre"], "631": ["Santa Mnria", "Santa Mlarla", "Santa Mlaria", "Santa Mla-", "Santa Mla-\nfia"], "632": ["AIIl", "IMI IAII", "IAIIIH\n-Sio Reis", "IAIIILS\nllento", "IAIIILS", "Ils"], "633": ["Ten", "l1 sta tentdu", "pe qte defrnto", "Tens", "tencbros0", "qte", "qten"], "634": ["Vao", "Yoltava", "Yolto", "Yolto derradamcnte i ema", "rcmolto cestiuho"], "635": ["Noronhal", "Noronha", "Noronhas", "tamilia Noronhal", "Nuronha"], "636": ["ga quanudo hega", "iudo", "Inudo", "quanudo"], "637": ["embaracados", "Praca", "lraca", "Snr' D. Gracu", "graca do sveu", "graca", "graca dos\ntromitos daza", "Graca"], "638": ["l-\nIou", "o-\nIo", "esbo-\nIado"], "639": ["barbaean", "barbeava", "barb"], "640": ["Ietras", "traidr", "lJltra-mar", "ultragge", "traeos", "ITra-\ngo", "tra"], "641": ["liomal", "mals", "Guiomar", "Iom"], "642": ["Arcada", "dua Arcada", "aa Arclivo"], "643": ["Olivira", "Pervira", "levia", "Tavira", "levira"], "644": ["Apparecel", "Appareca tam-\nbem", "desappareceru", "nio apparecu", "lieapparecend0"], "645": ["d'hera", "s6 pelu soberana alturu", "saherania", "saherania tdt"], "646": ["espaeo", "Paeo", "d'alpaea", "Paelo", "Paea", "Pae"], "647": ["mne", "Ilomnem", "Lom", "rclombou", "Nem"], "648": ["escoeo", "beh", "buschl", "Cusa", "Cusco", "lusco fusco"], "649": ["Lamara...", "Cumaras", "Cam1a", "Camara", "Camala", "campes", "Lamara", "Paire Amaro", "Presidente da Camara", "camape", "Amarante", "-HE", "relogio da Camara", "Camaras"], "650": ["n amigu seri", "Post-Seripum", "misoricordia", "Mlisericordia", "pu-\nhd0 0 cordio", "enore Rico-", "plcjad", "Mlisericrdia"], "651": ["Litteralura", "curapco", "Mlurad", "Clura"], "652": ["Alcmtcjo", "vcjo", "Alcu"], "653": ["acopanhira", "Manh", "manhai porm", "manhii", "Amanhi", "tanhi", "MIas de manhi", "Iuantas manhis", "Noella-recebeu do manhi", "Una mnanhi", "sc arredira\n'ssa manha", "anhi", "Amanha"], "654": ["Inagarefes", "peonagehi", "Inagnilicos", "Inagra", "Inag"], "655": ["quintciro", "quinlta", "El-ei tem uta\nquinta", "quintu", "laoaquina", "Quinta\nfcira"], "656": ["aui", "naui"], "657": ["relluem", "Torel", "Rel", "rela"], "658": ["despcdiu", "despcito tao", "lespcdacci"], "659": ["Mloral", "Mlorte", "Sorra Mlorcna", "Mlohiqtue", "Mlorle", "Iwis"], "660": ["Talvcz", "Acal", "calp0s", "calv0", "Culcalu"], "661": ["rmpendu", "hatendu", "novo retervendu", "Iacatent", "batendu"], "662": ["Pinhal\nde Estoevinha", "vinhu", "Gravinha", "cutello minha dce matdre Hstevani-\nnha", "Estevinha"], "663": ["libcira", "Cerejcira", "Ciil de Olicira", "Tecedciras", "cirado", "Oliycira", "b)edicira", "Irontcira", "pratelcira", "Alcira"], "664": ["p0", "lm", "Chole", "techot", "puehot o"], "665": ["apagadu", "mattagal", "afaga4am", "Vagarsalnclie", "Pruaga", "nhaga", "tGaga", "Aga-"], "666": ["Iebres", "bre", "resoou", "gresa", "tebres"], "667": ["Pedrosa", "pedru", "Vidros", "edro"], "668": ["Iha", "ombrulhado", "uiIhado", "elnmarauhado"], "669": ["qtlanto", "Ranto", "santos", "Iortanto", "rapazsl Santo", "Santo", "innnuveisl Santo IDeusl Mlortos", "Santos", "santol\n.--Ora", "Antonia", "Hspantos", "Santo beus7"], "670": ["Caalliro", "pallido", "Caalleio", "Cnvalliro", "AtC alli"], "671": ["sedinhn", "endinha", "Yendinha"], "672": ["Inostrou", "Iino", "iin-", "es Inostrar", "Iinos", "ui bciin", "pos linos", "Iinos cyprestes", "Inos"], "673": ["eia da tade In\ntGonealo", "Gioneale", "YtCZ", "oneal0", "tonealinho", "Gonea-", "Gonealol", "Niol Goneal", "Goneala", "Gonealinho", "Imnanos\nGonealo", "Goneal", "Gonealt", "Coneala", "Iaort- tGoneal", "Goneulo"], "674": ["dcsde", "surprchendcssecm", "surprceza", "Vendcia"], "675": ["gria", "Syria", "pria", "IPIria-  coi", "Iria", "MIayria paro"], "676": ["lisboa\nllces", "Lisboal\nNem", "Lisboa...", "l.isboa", "Lisboa", "Lisbona", "Lisboal", "lLisboa", "Iisboa", "ILisboa", "ci lisboa", "OII Lisboa", "dc Lisboa", "lisboa", "I6", "ksta t\nlLisboa", "Iisbou"], "677": ["abrissc", "Abria", "Abril", "Fabrica", "d'Abril", "HE", "voril"], "678": ["Meda", "Redacges", "greda", "gre", "Arreda"], "679": ["Poreira", "porei", "crei", "pore", "llestava porei"], "680": ["declrotu", "ondec", "IL0g0", "recspondela", "eseondessen1 U Olll1", "ondc", "Viseonde", "Mondes", "Viscuonde"], "681": ["ILl", "utros ullre", "ILLRE", "ILlremcnle"], "682": ["U ne", "D)'um", "arrastira n'umas andas", "1F\nd'ahi n'uma ba earavaua", "u n'um"], "683": ["Beml", "beml", "tatbem", "beml\nesteirada", "Tabemn"], "684": ["louvadol", "luva", "obruva"], "685": ["nio alvorolar", "ue nio der-\nribara", "nio dais", "eio l", "nio disfarea", "nio mc", "nio ha sulti-\nIleas"], "686": ["hmen", "Menules", "livremenle", "gemend", "homen"], "687": ["trespassado", "tres almogavres", "Tres", "maTia\ntra tres\ndestemido-qne", "retrescou"], "688": ["marroquim", "uuirroquim"], "689": ["terver", "intervcio", "cnternecido", "interessdo"], "690": ["Joaqtuim da Porta", "Joaqui", "Jouquim da\nCpa", "Joaquim da lParte", "Joaquim da Pota", "nhm d'Aquilut"], "691": ["mfim", "Hmfim", "Emfim", "mfin", "kmfim"], "692": ["formoso Leonel", "rmo", "tao formosa", "Formosa"], "693": ["alnas", "Inas", "las ahnas .fIonsinas", "Minas", "Inasstdos", "aenas", "Inas\naio emrelcndemosl..", "Mlinas", "demoradu Inas"], "694": ["Tarrel", "borla do harrete", "carrelra", "Tarre", "Trrel", "tarror", "caix\nde tartaruga"], "695": ["estrada de Collaros", "estrebuchaudo", "estrad", "a-\nlestra", "estruda", "testeira rostrada- semnpre", "tradici", "estrada\nAgora prim"], "696": ["IUosa", "IRkosa", "Kosa"], "697": ["saber1", "Sabes", "saberia narra", "Sabels", "Saber"], "698": ["lanqes om", "An-\ndre, scm", "Can-", "Lan-", "tan-", "Mran-"], "699": ["pclludo", "nio alludamos Iais", "pclluda", "tnludc", "Iepulud"], "700": ["io vi-\nsitnr", "Vi-", "vi-\ndraas", "petdra"], "701": ["Lnargo d'El-Rei", "ILargo d'Fl-lei", "U CsaSo d'es-", "Fl-ei", "Largo do Chalariz", "Largo d`Fl-\nei", "alagado d'esput", "Largo d'El-el", "Largo dEl-llei"], "702": ["piedade", "soledade", "Piedade"], "703": ["Adian-", "Gadiana", "Adi-", "Adio", "ian0"], "704": ["Gungalo", "Gongalo", "Gongealo", "Gongca-", "Gongcalo", "hengala", "ongalinlo"], "705": ["cgua", "Iagua", "gualrdado0", "egua"], "706": ["Alcaide dAveyras", "Ave-", "lyra", "Plavras", "Aveyras", "gavetao"], "707": ["tlivoirn", "Olivoira", "d'Olivoeira", "d'Olivoira"], "708": ["RAMIIIES", "ILLITIII A1 II AMIIINS\ngenebra", "IAMIIIIES", "IIAMIIIES", "IIAIIIIIES", "ILAMIIIH5", "IAMIIIIE"], "709": ["Yae", "Assigna Y.", "Passira\nahi", "Passira", "Assi", "Assimn", "Crassa", "impassivol"], "710": ["tei", "Iteisla", "reeisu", "Tcisl", "Iepeis"], "711": ["Ilhodes", "Filho-d'Algo", "bilho", "Rocilho"], "712": ["eom", "IWIS\neom", "ineomodava", "Ceo", "ceomo"], "713": ["irmi", "u irmiie0", "Irmio", "RMIlS"], "714": ["sompre toliciosa", "I)as", "sompe", "sompre", "eomprida", "Fmpregos"], "715": ["I'uis", "Uis"], "716": ["Elduara", "puara", "uarmaraln", "d'Azuara"], "717": ["Cmuolino", "Ioos do Camolino", "carvalheiras do Casal No-", "cabo do camiuho do Nasecnte"], "718": ["cnversandw cum utn ho-", "onversa", "aversaa", "niversal", "conversand0", "scmssaboria universal", "Rsa"], "719": ["ute i", "i cautela", "rutestar", "Uh", "ute", "Paroecc qute nel"], "720": ["llla", "lla\ndias", "lla", "klla"], "721": ["Por-", "Porgal", "porl", "IPor", "lPor"], "722": ["qute\nelle collabrava", "qute\nelle", "andre\nElle", "qte\nelle"], "723": ["Iais alto", "Waltor", "ceu alto", "lais aui", "ais alta"], "724": ["Inur", "Inuro", "Inuros", "uI\nnur0"], "725": ["liraria", "Snf IRartr", "Livraria", "Liraria"], "726": ["VWi-", "l)ueado le Galilea", "Galilea", "Afoguead"], "727": ["Mlanoelzinho", "apcrtda azinhnga", "Bm", "Mlanoel", "Manoelsinho"], "728": ["Formalra", "Formatura", "la Formatura"], "729": ["sobreveste ne-\ngra", "sobreeasaca", "sobrctudo de verio", "sobrc", "Sobras", "sobrc\nfeira de manha", "sobrecnsa"], "730": ["Castaheiro", "Castanheira", "Castanleiro", "Castanhciro Palrioti-\nheiro", "Castanhciro", "cothanheiru", "companheiru", "Castanhtei-", "Castanheiro", "Castanheio", "Castanheciro", "Castanhiro"], "731": ["uo vocs quizerem:", "Nocs", "Vocs"], "732": ["sahida da\nmissal Ao", "sahia", "sahi", "benta i sahida", "sahiu", "Sahira", "Sahi", "xira sahir", "sobesahir"], "733": ["tdos", "Iodos", "lodo bolsar", "Iodosas"], "734": ["to negre", "alegre", "exagvro alegrc", "alegree", "Egrcja", "msyo"], "735": ["Torre de l. Hamiresns", "AMIRE\n\nBolos de bacalhaul", "Torre de I. Hamires", "Torre de I. Raires", "Dize I.", "treire de an-", "Torre de mandudo do"], "736": ["Join", "Toi", "Toin"], "737": ["Toios", "receioso", "Ios", "Ios-"], "738": ["islricto", "Districto", "Auctoridle do Districta\nrcontra", "Iistricto", "Chefo do District", "distriet", "Chcete do bistricta", "L.lvdis", "distrahidas:- h."], "739": ["Iovrhgec", "Tovrvre", "arvrecdo"], "740": ["mctte", "qtte", "ttes", "fcrvuru picattte"], "741": ["tnuito", "Inuito", "sequito", "nuito serio", "Inuito noa", "Iuito", "uito"], "742": ["gales", "Froalengo", "dale", "ji sale", "caleil", "valenlias", "ale", "cale", "saler"], "743": ["Palrc Sueiro", "ceiro", "Sueiro", "vczeiro", "bom Padre Sueiro"], "744": ["i Auctri-", "iriio", "ms siio", "triio", "Guiio"], "745": ["Iinita", "gritand", "gtitar", "ra hnitau", "ine-\nitaveis", "jd", "Aquitania", "Coitadal", "Ita", "Mluitas", "Mloahitas", "resuscitar ostcs va-\nries"], "746": ["SC Io", "Ii", "u Iof", "sc Nro", "sc csse", "sc socgo"], "747": ["Palacio de gsto\nitaliano", "Fatali-", "hortalia", "Italia", "ltalia", "Italianos", "Bonital"], "748": ["m go", "Joao Gou-", "Joao Gouvcia", "MIas o\nJoao Gouveia", "Ioao"], "749": ["lovar", "lcvar", "urze", "varzea"], "750": ["vomo escre-\nveu", "escrceva", "escrvr ct garho", "Scrpftu-", "Scritum"], "751": ["partidus de lidye", "Partidol", "IPartido-"], "752": ["Losta", "Iloste", "la lloste leal\n1", "Felost...", "loste", "loso", "IIoste Ilcal"], "753": ["Sulares\nrivaes", "aes Iravaes", "Iravacs", "Vae", "Iravaes", "Bravaes", "urmurava", "ravaes", "St cspcrava", "prearava"], "754": ["tostoes", "Agosto", "lde haver tdesgosto", "gostol", "n'este Agosto", "hoston"], "755": ["Collares", "collao", "collo da mae", "ollal", "collina", "Gll"], "756": ["Entao", "kntao", "Nntao", "Fntao", "Intao", "Catao"], "757": ["coinbinarmos", "go", "loino", "coino", "coIno"], "758": ["Nlirauie", "Par;ira", "iradignio", "almcjira", "amira", "muira", "dmiraa", "estoira.-", "exclainira", "topira", "pquno", "Duxira", "mudira u", "alastrira", "sira", "coira", "IutIuUira"], "759": ["ma milha", "Iilha", "lilha", "nira\nau lilha ais nova de\nde 5", "rodilhado tropol", "ilha dum carniceiro", "humilhacio"], "760": ["Mlirnle", "Mlirnto", "Gnle", "Mlira-", "Mlirunte"], "761": ["Toa d'r-", "Toa d'r-\nl"], "762": ["Mauael", "Maus", "Mauael da Adega"], "763": ["sa tace mis", "iace do Fi-", "ge do Lnrg", "a6", "face do homcm"], "764": ["Jhle", "Nl-hley"], "765": ["eino", "Reino", "veridico do leino", "Icino", "Hleino"], "766": ["rioda", "Ioda"], "767": ["dalma", "passo tqute dve calmar", "Lma", "Alma", "Almas"], "768": ["nuca", "Goucaloe", "pouc0"], "769": ["dua Parada", "IPara", "plcparadu", "colsl\ndisparates", "Parahcens", "Parada", "lPara"], "770": ["lEste ul-\ntrajc revoltira o solar", "voltu", "voltassve", "Volteos", "volvu:-", "GA", "altuc"], "771": ["aneiras", "Tecedeiras", "Seira\nI168", "seiras", "seI", "hom-\nhreiras", "uin cruseir", "Mareiras"], "772": ["valle estreito dc Canta-Pcdra", "estreito dc Canta-Pcdra", "pcdra", "Erncsto dc"], "773": ["Iiscutal", "Iiscurso", "Viscunde"], "774": ["immensissima", "immehsa", "ma immensa ve`gouha", "tcm immens0", "Iens", "immensos", "p6de"], "775": ["Iorrc", "Irrc", "Torrc", "lh ua Torrc", "Torrciro do Paco"], "776": ["braza", "braz", "abrazaa", "Brazil"], "777": ["Vivaonle", "Vival", "lival qunndo", "Vivaln\nMIagestosamente", "IVa3", "divan"], "778": ["plorando ny", "ameagira", "girand", "se-\ngirand", "iugira", "diran", "Casal do\nMliranda"], "779": ["maos", "Iaos", "mao", "Raos"], "780": ["Quartel", "luarte", "Baluarte-Volho", "l2art", "Iuarte"], "781": ["Fleitores", "Leit", "lois leitDes"], "782": ["r,,- l", "lelogio-de-Sol", "Tolelo", "Seplelo", "intolesr.-"], "783": ["Manso", "io-Mans", "Rio-Manso"], "784": ["vinganga", "fnga", "descanga", "Vingasse", "langas", "gingand", "nanga", "engasg0"], "785": ["IMII", "U.AA I IMIIS", "IMIIlI5", "MIi-", "IIMIIIH", "C.A1 I. IMIII"], "786": ["Geuealoic", "Guonealo", "unealo nascira", "inealo", "Gunealo", "Gouealo"], "787": ["Admi-\nnistradr", "Administrador", "Administradr", "Aministrador", "Ainistralor", "hraco do Admi-\nnistrador", "Ainistrador", "Amninistracio", "lministrador", "Aministrador do Concelho"], "788": ["Te-Deum", "bDeus", "IDeus", "Deusl", "merce de\nDeusl", "bDeus noss", "Deus", "Ieus"], "789": ["grossu", "N'ossa", "uossa", "cssa", "poss0", "Russa"], "790": ["gre amael", "Melodrama", "Mlama", "nama"], "791": ["Bayao", "U\ndesar0tl", "sen Cayal-", "desfazcr", "deses-1", "desdohaya"], "792": ["Ilespa-\nnha n'uma pandega heroical", "Mlespanha", "Ilespanha", "llespanha", "Ilespa-", "dIIospanha", "IIespanha"], "793": ["aloro", "Palo", "Alon-", "alol", "Gaualo"], "794": ["lraaua", "iemlra", "Iem", "Hlra-"], "795": ["Joio Gouveia", "Joio ouveia", "Joiio Gouveia", "Joaio Gouveia", "lio Gouveia", "portao Joio Gouveia"], "796": ["Ceo accuda", "caheeo alto", "dce\nchapeu alto", "haneo alto", "chapeo alto", "chapeo", "letle l\nvelho chapeo de palha", "Peo s Mi-\nchas"], "797": ["pobe da vclha", "parclha", "tclhado", "vclha", "orclha"], "798": ["IJoa", "Joa-", "Joa"], "799": ["tonalo", "Gonalol", "Uonalo", "Gonal0", "tGonalo", "Gonalo aeudiu", "Uaonalo", "Gonalo endes", "Gonalo", "F Gonalo", "Ohi Gonalo", "eglonalista", "Gonal"], "800": ["segurand", "estendid l t plitrona ii vurand", "ii vurand"], "801": ["Coraon", "Nacao", "coracao", "Coral", "Oracas", "coraci nio"], "802": ["Cilude", "cilua", "lua", "luancns", "Ilu"], "803": ["scgulia", "CUlII", "Clul", "lulia", "Mlultidio", "liaI0'C"], "804": ["Snr\nIlegedor", "Sbedores", "Yedor", "Saledor"], "805": ["Fidulgol meu Fidalgol", "Ulgoso", "F6ra", "Fidulgo", "Iidulguia"], "806": ["apa-\nvorira", "apa-", "a4pa-"], "807": ["lapide", "papi", "IIDE3", "lapis", "brancuras de lapides"], "808": ["Jutubro", "uI\nbro", "subro"], "809": ["quietaeao", "quietaco", "ji inuieto"], "810": ["raoean-I\ndo u lcito de pau pret", "pcito", "lcito u tad", "aceccitou", "Hrito", "IBrito", "effcito"], "811": ["Ccm", "d'Aellim", "sellim", "Ai", "l'aeos d'Aellim"], "812": ["Santa-Ireneia", "Santa-lrrneia", "Santa-lreneia", "Fnlgeneiao", "Santa\nlreneia", "Santa-lrneia", "Santa-lreneiu", "lreneia"], "813": ["Salcdor", "mcdo c", "hocdo", "Feiosn n Trei-\nxcdo"], "814": ["Hlica-Ilo-", "sc puhlicass", "pa pu-\nblica", "dolicassc"], "815": ["Valerde", "Yillaverde", "Valverde", "Verde", "chi verde", "elo Verde", "Yalverdc", "erista dos outirs de\nYalverde", "Caho Verde"], "816": ["indule", "Aindu", "ria aindu"], "817": ["Sino de anlua", "convento das\nonicas", "Convento de anta-lIlrigida", "Convento de anta-lIlrigida do", "lnveneao", "convento de Santa hereza"], "818": ["agua fresea", "Ireseos", "Ireseo rebrilho dos dontes", "Ireseo", "deseoherta"], "819": ["pasmad0", "ncsma", "IncSI10"], "820": ["Reriz", "Clerigo", "Romperia", "eautels du Loleria", "Loleria"], "821": ["IEl-lei", "El-lei", "El-lei Fer-\nnando", "El-kei"], "822": ["Iargeln", "Jargo", "Iargo", "Iargu", "Qe"], "823": ["S. Fulgeneio", "S. Fulgcncio", "Fulgcncio", "V. F"], "824": ["Safa", "Largo do Chafariz", "Clafariz", "Chafariz", "Chafriz"], "825": ["Fnthusiasmo", "relusia", "quusi"], "826": ["Gunalo", "Ganalo", "Inalo  in perceo", "Gunal", "Gnalo"], "827": ["claustra", "Claustro", "Castrol"], "828": ["mlim", "gentel\nmlim tica", "Fmlim", "jarlim", "emlim", "Hmlim"], "829": ["belegado", "Delegado", "es"], "830": ["Tcixeira de Carredes", "ribeira de\nCrede", "Teixeira de\nCarredes"], "831": ["Guedes", "uedes", "Vede", "guedelha", "Gedes"], "832": ["csfurucando", "seccalrcm", "seccando", "candcia", "Irincando", "secco"], "833": ["ac", "Aggora", "aggo"]}