{"-1": ["PLAIN STATEMENT", "UNDERSELL", "Leeds", "Warwick", "Providence", "Tilbury Fort", "Foxglove", "Deep", "France", "MR", "Helvellyn", "Deep-Valley", "morocco", "Great", "Sèvre china", "Charlotte", "NURSE", "Louisa", "Cannon", "Paris", "Saxony", "M.D.", "Venus", "Mexico", "Scotland", "Cretan", "MS", "Shakspeare", "Flanders"], "0": ["Samaritan", "Britain", "Spain", "Italy"], "1": ["inn", "woodbine", "Turpin", "Turkey"], "2": ["Prentice", "orient", "Nice"], "3": ["America", "Africa"], "4": ["Wakefield", "Sykeses", "premises", "Drakes"], "5": ["Prescot", "Scotch"], "6": ["Poland", "Westmorland", "England", "Highland"], "7": ["Madeira", "London Madeira", "Golconda", "Cologne", "London"], "8": ["Lancashire", "Lancashirc"], "9": ["York", "Yorkshire"], "10": ["DERBYSHIRE", "Derbyshire"], "11": ["Neckerby", "Rebecca", "Blackberry", "Becky"], "12": ["Hoxley", "Crockley"], "13": ["Valley", "VALLEY"], "14": ["Deep Valley", "Deep\n     Valley"], "15": ["the Deep Valley", "THE DEEP VALLEY"], "16": ["the Deep Valley Mill", "Deep Valley Mill"], "17": ["Millocrats", "Mill"], "18": ["Milford", "Millford Park", "Milford Park"], "19": ["Bradford", "Oxford"], "20": ["Bastille", "East"], "21": ["North", "Wordsworth", "earth"], "22": ["Crompton", "Brotherton", "Rome", "Boston"], "23": ["the Emerald Isle", "the moon", "the Holy Virgin"], "24": ["Halloo", "Halifax"], "25": ["Protégée", "protégée", "protegé"], "26": ["Russia", "Austria", "Rasselas", "Brussels"], "27": ["St.\n     Mary's", "St. Mary's", "St."], "28": ["Thistledown", "Dowling"], "29": ["Germany", "Ulswater", "Kidderminster"], "30": ["Sophy", "Europe"]}