{"0": ["rse", "perse", "Aprs", "Bourse", "0hl", "eparse", "rs", "se6-", "Doses"], "1": ["O2", "sg", "Kg", "sgf"], "2": ["Ll", "college", "Folle", "Llle", "tranquille", "besoin.n\nLlle", "Rollebose", "daille", "Lllesentit"], "3": ["mer par-dessus", "paris", "Paris", "Paris 7 A", "enlaceesparfois", "Parfois", "Ne le faispas tantparler"], "4": ["au-\nT\nL", "N.", "E\n\nI.\nL\n2t\nE2", "e21"], "5": ["terre de Barville", "La grosse couleur de cette reference obstine\ne Peul :por cette ereature", "M. de Brisbane", "Lexpertise des Vaud", "Darriere blanche", "jeter blanche de", "gare de Beuzeville", "mre Couillard", "couvent\nt te preoccupee de l'avenir", "moselle de la Roche-Aubert", "fosse des\nbillard", "chateau de la Villette"], "6": ["lejeune", "Lejeune", "h"], "7": ["aussit0", "Aussitot", "Yauseotte", "R"], "8": ["Is", "LMIais", "bois bruni", "is", "N0I", "i\n\nPis", "Nais", "Pis", "o Puis", "O", "Fais", "Pois"], "9": ["Es-tu malade", "deMadereet", "degel", "Adelaide", "bade", "Rigide"], "10": ["les Fourville", "mouille", "Courville", "Fourville", "Gourville", "Goderville", "ouville", "four", "Barville", "nee Fourville", "Gdoderville", "e Fourville", "Godarville"], "11": ["Visionnant...", "AnNon", "roninlanoligue", "Mignonne", "Nonnous-en", "Visionnant"], "12": ["Asaln", "LN", "Ln"], "13": ["E-", "Me-", "de-"], "14": ["Coursi-", "commetoujours", "Coursil", "accoutumee  la lancolie des journes"], "15": ["Tenez", "Vienne", "EtIEnne", "enne", "Athenes", "Enne", "Jenne"], "16": ["rEn", "Couvrent", "Comprendre", "Reviendra", "dore", "Isurent", "nOuirent", "Renard", "Ressentit", "choire", "Rentrons"], "17": ["la caleche", "ALLI", "alle", "La valence", "AlLergique", "AL", "valley", "1R 1", "L176", "Yos alle", "Aller-", "Allemagne", "Allez"], "18": ["B", "able Tolbiae", "Ia", "Tolbiae", "Bolbec", "Tolbiac"], "19": ["Lors'", "salo", "Lorsquon", "alors7", "alors?n", "AlOrs", "Lor", "Dors"], "20": ["song6e", "so", "bient0t Lison", "Lison", "Maison"], "21": ["rue du Sauvage", "suva", "golfe de Sagone", "rue\nsaUvage", "sauVa", "I rue du Sauvage"], "22": ["Ykport", "apporte-les-moi", "Port", "H", "h Yport", "Yport", "Qrti"], "23": ["Maisy", "Maie", "implora;mais", "Lait", "Aimait", "Cotait", "AI"], "24": ["ca", "calme-toi", "sCa", "Cargese", "Ca", "calm6", "caf6"], "25": ["le Havre", "du Havre", "college du Havre", "Havre", "hA", "rue du Havre", "au Havre"], "26": ["Interpr", "hesiter", "Lhiver", "nigeria", "vert-de-gris", "guier", "er", "ger", "la-Vierge", "fiert6", "cherbourg", "nent.oserais-tu demander", "LEr", "Affoler", "A1"], "27": ["coutez-moi\nien", "teaudun", "Laroute", "Coutelier", "Couteaux", "gteaux", "eaU-"], "28": ["maman", "Damas", "Amazone", "Flamands", "nima", "Madame.n", "malgr", "manche", "Mars"], "29": ["miserieorde", "Pourriez-", "Cri-", "lhorizon", "Marieel", "ri", "Oriental", "orie"], "30": ["Chine", "chine", "5Z", "Chinois", "la Seine", "champagne", "rhin", "tine", "dine", "Vitrine"], "31": ["Yontivilliers", "tiede", "lIe", "oubli6e", "Lieu", "Ms", "lituANIE", "Italie", "Incolie", "Rosalie", "sieJulien", "gie", "WIE", "lit'", "d'Italie", "RoSALIE", "crmonie"], "32": ["celane", "elan", "Las", "Jas", "as304", "Elas", "Lastique", "el"], "33": ["rosinquil", "Cequilui", "LIL", "Voil", "IIL", "il158", "gil", "IL", "Ilse", "Pail", "neil.s'"], "34": ["Cigogne", "Cologne", "G", "besogne", "resignee", "cigogne"], "35": ["g85", ".G", ".g"], "36": ["Impuret", "courbaturee", "Cepteur", "yeu", "deurope", "heuressans", "Harfleur", "murmure:4Ditesdsnc", "eure", "sAcre-Leur"], "37": ["abbaye Picot", "becota", "Picot", "tricotan", "01C1", "tricot"], "38": ["Ocean", "oceupees", "oCean", "z:::ocz", "eA"], "39": ["Leattendait", "Entend", "Lentement", "Dentu", "romputientatilattu barquement", "Sainte-Helene", "en'", "Attend", "ferente"], "40": ["Brisseville", "vicomtesse de Libreville", "les Libreville", "Varneville", "Beuzeville", "Libreville", "tibre issu'", "Watteville.29\nUNE VIE\nPuis"], "41": ["Cu", "percut", "L\nCu", "yecu", "cupour"], "42": ["Vrai", "brassa", "auraitbesoin", "souffleterai", "rai", "rai-LNE VE", "raye6", "jura", "arras", "vrai.-n,-", "Ilaurait", "Vitrail", "Pyrame"], "43": ["Corse", "La Corse", "Corse d'Evisa", "YIE\ncorse", "I petite Corse", "la Corse"], "44": ["le soleil", "soleil", "Leopold-", "Mle marseille", "sOleil", "P", "Napoleonl", "Le soleil"], "45": ["Lbarone", "garonne", "Baronne", "argonne", "s6", "garon", "Ias 1e baron", "La garonne"], "46": ["tete", "Tes", "Comptez", "bete", "C0te  cute", "La sonnette", "C0te", "sa`casquette", "bete crispee", "Cettepauvre", "determinee", "Tete", "Cite", "honteuse"], "47": ["bois du siege", "11asi", "asie", "siege", "sie", "--Si"], "48": ["gr carter", "lherte", "Thysbe", "gilberte", "comtesse Gilberte", "Gilberte", "Pertes"], "49": ["Normande", "Normandie", "Normand"], "50": ["bondit", "Diable", "Dn", "lunit", "Mediterranee", "poprit,'q'", "Dit", "Die"], "51": ["-  Pas", "etais pas sr", "- Ah"], "52": ["nelle", "ELle", "Pelle", "bellecour", "1Elle", "HLELY", "Ellerentrait", "ellepassa", "naelle", "Ellebuvait", "eleganee", "femeLle", "sele", "mis.elle", "Est-elle", "Relev"], "53": ["jei", "EI", "deia", "oeil"], "54": ["ILe", "mobile", "Villette", "Ilet", "Paulet", "cabinet de\ntoilette", "Ile"], "55": ["Cany", "Cana", "ny"], "56": ["parcimonie france", "Puissance", "France", "france", "Trange"], "57": ["nes-tu satisfaite7", "Vois-tu", "Veu-tu", "connais-tu", "Va-t'", "Voie", "vois-tu", "fRais-tu"], "58": ["Omme", "Homonyme", "lanmme", "Immense", "fom"], "59": ["MI", "lemire", "Mie", "Midi"], "60": ["toul", "choua", "tOurs", "toutou", "ettout", "Ou'"], "61": ["lampe ets'", "fEh", "Fecamp", "F6camp", "phare de Fecamp"], "62": ["Crott", "troyes", "Fuyez", "dployes", "Croyez-"], "63": ["R2", "IIs", "MIis", "iIs", "Iis", "Iii:.i\nlure pas eisore faim"], "64": ["I\nH.", "U", "D140", "I\nD180"], "65": ["Bastia", "mer l-\nbas", "L-bas", "Lh-bas", "L-", "E1", "lh-bas", "la-bas"], "66": ["affaissee", "Palais-Royal", "Encaisser", "ladresse", "laissantvide", "Vaisselle", "Laisse", "Laisse-", "Laissait", "Anglais", "E.sembla"], "67": ["Lapons", "mons", "Allons", "Bonsoiro", "lons", "Voyons"], "68": ["Combien", "bir", "Etaient-", "Bientot", "bIentot", "Tot", "N", "Tiens", "bientot"], "69": ["sauta", "beaut", "Autrot", "el haut", "E", "Faut", "Hauts", "auteuil", "Seautage", "D94", "Ilfaut"], "70": ["lvres", "tre talus", "riatres", "Apres", "Notre-Dame du Gros-Ventre", "L\natre", "Litres", "Trois-Mares", "tressailli", "Ap0tres", "lares-midi", "resolut", "Lautre", "tres", "Chicorees", "tres bas"], "71": ["considerersa", "derribre", "Elerecut", "Ladultere", "Rer", "soutanerebondie auxerre", "Eretry", "Petite mere", "eolre", "Angleterre", "severe", "perret", "tes leir eri maigre", "Aa here rils"], "72": ["Artois", "artois"], "73": ["G55", "Corniche", "Drnee", "Rn", "rn1y"], "74": ["val d'Ota", "val d'ota", "D64", "Val"], "75": ["IH", "Provence", "Providence", "CCPr"], "76": ["LEs", "arles", "V1LE", "chateau des\nPeuples", "Peuples", "angeles", "Rales", "Maleleines", "lesoitriers", "anneblessee", "Naples", "accables", "lescopes", "bou6es", "Lectro", "leslesfetes.-"], "77": ["Voulez", "Poulet", "voulez", "VOus"], "78": ["Ganaehe", "aC'", "Ganache", "laceouchee", "he", "Piana", "lche"], "79": ["I\n\nC.\n\n2", "I3\n\nI\n\na-.. /\nr'\n1y", "C.:3", "I\n\nH."], "80": ["Saint-Leonard", "M", "ainail", "Touraine", "romains", "tina", "Romaines", "Ina", "sapins", "Soudain", "ain"], "81": ["Evisa", "lavie", "viE.", "vI", "G'", "VI"], "82": ["Lendemain", "Indes", "Indes privilegiees", "mondeet", "I", "inde", "malheursindeinis", "candelabres", "Aucunbesoin", "Aeondes"], "83": ["-Oui", "lou-lou", "ROi-Louis", "Roi-Louis", "Loir"], "84": ["gnt", "trebuchant", "point-la", "L nant", "Anti-physiques", "Tant0", "Santo", "Instants", "dinant", "IQans", "lancolie m6ditant", "Ant", "tant0t", "trante"], "85": ["Versailles", "Rriseville", "seveiller", "Marseille", "lachete\n us conseille", "bouleversee", "Sacre-Corneille", "Verneuil", "laveille", "reveillee", "loreille"], "86": ["Pays", "guyane es paysans", "pays de Ceux", "Pas de lune", "Ceux"], "87": ["piece", "Chambre-aux-Demoiselles", "sambre", "l'Empire", "Grece", "Decembre"], "88": ["Ia \nneto", "guyane", "gane", "NE", "Done", "Enehatnee", "I\n\nI\nI\n2.166\nUNE VIE", "Fine", "lune", "NE V1E", "hargne"], "89": ["Cemment", "meuse", "sume", "emea", "Eme", "Emmen-la"], "90": ["A", "I\n\nL.0", ".L.", ".--L."], "91": ["LBpetit", "Ilbalbutia", "balbutiont"], "92": ["Leestendres", "ch-\nt Est", "Cest", "estauand", "Est"], "93": ["pls", "Lac", "large.-", "La plaine", "Pla", "laga", "platre"], "94": ["Iowa", "rion", "Io", "Niolu", "E5s", "D", "io\n Eg", "Ajaccio"], "95": ["Re-re-garde Ma-MIa", "gardee", "san regard", "ZEg", "Jardin", "lagarde", "Regarde", "abregea"], "96": ["Jeannemurmura", "Jeane", "chambre de Jeanne", "t Jeanne", "jeanie"], "97": ["Lhabitude", "b6atitude", "Rouen", "mont Roudet", "Roudet"], "98": ["auxeglises", "Brise-", "surplis", "plissee", "Utilise", "lEglise", "Eglise", "alIS", "salis", "pise", "Leglise", "U NE vIE\neglise", "Lise", "oise", "SesCiSea"], "99": ["iii", "III", "II", "Iii:.i", "IIII\n\n12", "ii", "S", "H1", "Be\nII"], "100": ["Quelquefois", "e'", "quoi7", "que'", "Amerique", "Quelui"], "101": ["e", "Sa336", "plusqu'", "nousaviserons", "usa"], "102": ["UN", "un320", "D202", "A208"], "103": ["Londres", "etreindre", "Lepretreportele", "repondre", "londRes", "Querepondras-tu"], "104": ["Etat", "Eretat", "Jet'", "Palabretti", "Etretat"], "105": ["A\n\n\n Ch", "ch6e", "bauch6e"], "106": ["Beelzebuth", "eenrs", "convulsee", "aee", "EE", "abimee", "metiee"]}