{"0": ["Samboe", "Pembroke", "Feroe", "Feroe Islands", "Cicero", "Algiers", "Berry Pomeroy", "Euphrosyne"], "1": ["Caroline", "Lina", "Collins", "Halifax"], "2": ["Percy", "Percy?—let"], "3": ["INDIA", "Zenobia", "Edinburgh", "Harding", "India"], "4": ["Seaton", "Swansea", "T—.", "Hamilton", "the Sea Queen", "Torrington", "Ashburton", "London"], "5": ["Madeira", "Barbary", "Providence", "Denmark", "Sweden"], "6": ["Llangwillan", "Leander", "Glamorgan", "Moorlands", "England", "Old England", "Highland", "Ireland"], "7": ["Scotland", "Scotsmen", "Atlantic", "the Shetland Isles"], "8": ["child:—if", "MS", "vail"], "9": ["New York", "New-York", "NEW YORK"], "10": ["Caithness", "Harcourt", "thou", "Thou", "MR", "Elizabethan"], "11": ["Wales", "Bibles", "Esq", "Italy", "Psalm"], "12": ["me?—oh", "meek", "Cheltenham", "Seldon Grange", "Grahame", "Gehazi"], "13": ["Plymouth", "British America", "Truth", "South America"], "14": ["Ellen", "Seneca", "Helen", "faltered—\"Ellen", "Lascelles"], "15": ["Carmarthenshire", "Yorkshire", "Delmont", "Devonshire"], "16": ["Germany", "Greville Manor", "Manor"], "17": ["Easter", "Exeter", "Oakwood"], "18": ["Milford Haven", "Portsmouth", "North", "fort", "myrtle", "Oxford"]}