{"-1": ["hurle—", "Anges", "croyais", "—:-‘", "A‘-t-VOix—", "t’", "MARIE—CLAIRE 123\n\nj'avais", "tempes", "mur", "Miroir", "MARIE—CLAIRE 2 I\n\ne 'e'", "dugmæ", "Chicon", "auddetfm‘lesﬁgædecæù", "remarquai", "landiers;il", "Næsrzﬂioæàlæ=", "Gaboret", "onne", "Aimêe", "M", "buta", "Aucun", "Tunesäspeut—", ".\"1 lol—\\ l.il\\n.vîtl‘l", "E", "tulle", "I", "mxtæ", "üyadægædæmæpoæra—", "Mon Père-\nDieu", "v-", "trem—", "MARIE—CLAIRE 101", "rensei—", "dix—neuf", "et-", "La grosse cuillère", "c—", "I 22", "Maintenant", "dimi—", "m‘as", "Colette€\n\n—- Je", "VI\n\nOUT le Jour“ je pensai", "bonds", "pres—", "bles", "—moi", "40 MARIE—CLAIRE\n\nLa cloche du coucher", "Pas", "Ombreﬁnat", "«,-_-", "Dfaçon", "Pourquoi as-tu", "Tiens", "L", "mägréungﬂnd"], "0": ["C’", "!", "I'"], "1": [".:;‘J", "d’", "Mﬂ"], "2": ["m”.-$‘.wæw-&", ".-—v", "Lﬁt"], "3": ["A", "i’", "j’"], "4": ["AH", "AHﬁS"], "5": ["aussi‘", "Aussitôt"], "6": ["aussi—", "Aussi—"], "7": ["m’", "M’"], "8": ["Gué", "Gué Perdu", "château du Gué Perdu"], "9": ["arrê—", "Arrête"], "10": ["amI91", "amI87\n\nfe"], "11": ["kam—", "mam—", "mam"], "12": ["Sologne.ll", "Sologne"], "13": ["Bibiche", "Bibiche m’"], "14": ["Vin", "ca chœœ"], "15": ["So—", "Co—", "so—"], "16": ["Psadzxyt", "brassa"], "17": ["ﬂnlnnil", "s’", "Ils’"], "18": ["de France", "Tirande"], "19": ["Désirée-des-Ange", "Désirée-des-Anges"], "20": ["Désirée—des—Ange", "Désirée—des-Ange"], "21": ["horpmos", "mouy—"], "22": ["Est—ce", "@ce", "forCe", "t—"], "23": ["chauﬁer", "réchauﬁer"], "24": ["lingerie", "inﬂiger"], "25": ["Nﬁnis", "Enﬁn"], "26": ["la terre", "terre", "L-"], "27": ["agenouülée", "engage—"], "28": ["Coup", "bæucoup", "Iesecouai"], "29": ["auberge du", "Vierge"], "30": ["Ahñnﬁpæditpadenœetseœdt‘eæaendiæﬂ", "Et Dit"], "31": ["indiffé—", "brindülæ"], "32": ["eus l’", "Nous l’"], "33": ["intri—", "attend—"], "34": ["lavé", "largœ"], "35": ["._", "n__.", ".__—4_lA", ".—.—.___‘4-4 4"], "36": ["L’", "l’"], "37": ["je l’", "A l’"], "38": ["traî—", "entralna", "traî—\nnant", "traînéæ transparents"], "39": ["se-berçaitz", "Va", "eniamber", "Évait"], "40": ["La Saint-Jean", "Saint-Ian", "Saint-Jean"], "41": ["laSainte Table", "Saintes Huiles"], "42": ["Sainte-Montagne", "Sainte—Montagne"], "43": ["buis", "hruis—"], "44": ["châtaignieis", "Châtaigniers", "Uninsœnt"], "45": ["alors—", "mrs", "mrs—", "mars—"], "46": ["Communs", "chmæithcbaæondelîæu"], "47": ["Augustine", "Martine", "Ma1tine", "art(1"], "48": ["nourri—", "Aﬁnée", "tournai", "Journée", "tour—", "nour—", "bour—"], "49": ["l’heure", "heur—", "heure—"], "50": ["porte n’", "de—", "ﬁ De", "Te Deum"], "51": ["l-Œil", "Bel-Œil", "Bel—Œil"], "52": ["baron—", "non—", "répon—"], "53": ["Ismétie", "Ismérie", "Ismé-"], "54": ["Méanie", "Mélanie", "s&ie", "vnie", "Méla-"], "55": ["Allons", "long—"], "56": ["Santons", "santa"], "57": ["Combien", "bien—"], "58": ["cher—", "labou—"], "59": ["rappelez—", "Appela"], "60": ["mêmE69", "Elk www", "Mﬁelﬂœ", "Ele", "elme"], "61": ["Rome", "dome"], "62": ["muﬂ Qu‘elle", "poche;elle"], "63": ["leil", "Le soleil", "réveil—"], "64": ["réﬂécria", "décro—"], "65": ["créa—", "sépa—", "a—"], "66": ["funﬁer", "Aﬂﬁe;Un", "puriﬁer", "conﬁer"], "67": ["conﬁancre", "méﬁancre"], "68": ["Es-tu folle", "Es-tu malade {"], "69": ["beau—", "Blanche", "manche", "la Blanche", "blan—", "quan—", "beaulis blanc"], "70": ["Villevieüle", "Villevieﬂle", "Vﬂlevieille", "Vülevieille", "Villevieille", "Ville-"], "71": ["Castille", "Castle"], "72": ["trous—", "trou—", "brus—", "trouvais", "pous—", "Rouge"], "73": ["Appuyez", "Appuie"], "74": ["marchais", "cachai", "Cache"], "75": ["venaisde", "connais—"], "76": ["appré—", "approchai", "æsayai", "æsayai‘\nde m 'approcher de lui", "apprxs"], "77": ["quitterais", "serais"], "78": ["comparai", "comptais", "Iosentais", "reietais"], "79": ["Parfois", "Paris"], "80": ["Sois", "Deslois", "Vois"], "81": ["Aimée", "Marie—Aime", "Marie-Aimée", "MARIE—", "Marie—Aimée"], "82": ["repren—", "Prends", "reve—", "vre", "reﬂet"], "83": ["regar—", "appar—"], "84": ["sene", "Venez"], "85": ["Voulez", "voulais"], "86": ["notre Marie-Claire", "MARIE-CLAIRE"], "87": ["qu’", "Qudquæ-unænæe"], "88": ["Quelquefoîs", "Quelquefois", "ﬁque", "Quelque", "ques—"], "89": ["laissais", "Laisse", "Fais"], "90": ["MAis-", "i ’aimais"], "91": ["Eugène", ".ne"], "92": ["Jaune", "qu‘au", "qu‘une"], "93": ["MARIE—CLAIRE", "Marie—Claire"], "94": ["8 MARIE—CLAIRE", "48 MARIE—CLAIRE"], "95": ["52 MARIE—CLAIRE", "I 2 MARIE—CLAIRE"], "96": ["76 MARIE—CLAIRE", "100 MARIE—CLAIRE", "56 MARIE—CLAIRE", "36 MARIE—CLAIRE", "106 MARIE—CLAIRE"], "97": ["54 MARIE—CLAIRE", "44 MARIE—CLAIRE"]}